<?xml version="1.0" encoding="ISO-8859-1"?>
<WhiteboardCaptureSession>
  <WhiteboardDescription>
    <SensorLocation corner="top_left"/>
    <DiagonallyOppositeCoords x="6972" y="2470"/>
    <VerticallyOppositeCoords x="200" y="2470"/>
    <HorizontallyOppositeCoords x="6972" y="1947"/>
  </WhiteboardDescription>
  <StrokeSet>
    <Stroke colour="black" start_time="16029330.37" end_time="16029330.72">
      <Point x="307" y="2104" time="16029330.37"/>
      <Point x="345" y="2111" time="16029330.38"/>
      <Point x="338" y="2104" time="16029330.40"/>
      <Point x="329" y="2096" time="16029330.42"/>
      <Point x="318" y="2096" time="16029330.43"/>
      <Point x="300" y="2093" time="16029330.44"/>
      <Point x="277" y="2097" time="16029330.46"/>
      <Point x="251" y="2112" time="16029330.47"/>
      <Point x="236" y="2132" time="16029330.49"/>
      <Point x="226" y="2154" time="16029330.50"/>
      <Point x="216" y="2188" time="16029330.52"/>
      <Point x="210" y="2217" time="16029330.53"/>
      <Point x="202" y="2248" time="16029330.54"/>
      <Point x="200" y="2285" time="16029330.56"/>
      <Point x="201" y="2316" time="16029330.58"/>
      <Point x="207" y="2345" time="16029330.59"/>
      <Point x="214" y="2365" time="16029330.60"/>
      <Point x="226" y="2387" time="16029330.62"/>
      <Point x="244" y="2406" time="16029330.63"/>
      <Point x="265" y="2419" time="16029330.65"/>
      <Point x="287" y="2427" time="16029330.66"/>
      <Point x="315" y="2427" time="16029330.67"/>
      <Point x="340" y="2423" time="16029330.69"/>
      <Point x="361" y="2417" time="16029330.70"/>
      <Point x="374" y="2409" time="16029330.72"/>
    </Stroke>
    <Stroke colour="black" start_time="16029330.93" end_time="16029331.28">
      <Point x="460" y="2351" time="16029330.93"/>
      <Point x="472" y="2354" time="16029330.94"/>
      <Point x="480" y="2352" time="16029330.96"/>
      <Point x="489" y="2350" time="16029330.98"/>
      <Point x="494" y="2344" time="16029330.99"/>
      <Point x="498" y="2332" time="16029331.00"/>
      <Point x="498" y="2304" time="16029331.02"/>
      <Point x="492" y="2281" time="16029331.03"/>
      <Point x="485" y="2267" time="16029331.05"/>
      <Point x="477" y="2265" time="16029331.06"/>
      <Point x="467" y="2265" time="16029331.08"/>
      <Point x="454" y="2270" time="16029331.09"/>
      <Point x="440" y="2282" time="16029331.10"/>
      <Point x="428" y="2300" time="16029331.12"/>
      <Point x="419" y="2318" time="16029331.13"/>
      <Point x="412" y="2340" time="16029331.15"/>
      <Point x="410" y="2361" time="16029331.16"/>
      <Point x="412" y="2382" time="16029331.18"/>
      <Point x="424" y="2403" time="16029331.19"/>
      <Point x="439" y="2424" time="16029331.21"/>
      <Point x="456" y="2441" time="16029331.22"/>
      <Point x="473" y="2450" time="16029331.23"/>
      <Point x="488" y="2453" time="16029331.25"/>
      <Point x="501" y="2453" time="16029331.27"/>
      <Point x="515" y="2444" time="16029331.28"/>
    </Stroke>
    <Stroke colour="black" start_time="16029331.47" end_time="16029332.00">
      <Point x="644" y="2334" time="16029331.47"/>
      <Point x="653" y="2331" time="16029331.49"/>
      <Point x="655" y="2328" time="16029331.51"/>
      <Point x="655" y="2328" time="16029331.52"/>
      <Point x="648" y="2309" time="16029331.54"/>
      <Point x="634" y="2291" time="16029331.55"/>
      <Point x="615" y="2274" time="16029331.57"/>
      <Point x="595" y="2262" time="16029331.58"/>
      <Point x="579" y="2258" time="16029331.59"/>
      <Point x="569" y="2268" time="16029331.61"/>
      <Point x="564" y="2279" time="16029331.65"/>
      <Point x="564" y="2296" time="16029331.66"/>
      <Point x="569" y="2326" time="16029331.66"/>
      <Point x="581" y="2348" time="16029331.67"/>
      <Point x="595" y="2376" time="16029331.68"/>
      <Point x="610" y="2400" time="16029331.70"/>
      <Point x="622" y="2415" time="16029331.71"/>
      <Point x="631" y="2425" time="16029331.73"/>
      <Point x="638" y="2422" time="16029331.74"/>
      <Point x="647" y="2408" time="16029331.75"/>
      <Point x="656" y="2384" time="16029331.77"/>
      <Point x="663" y="2345" time="16029331.79"/>
      <Point x="665" y="2297" time="16029331.80"/>
      <Point x="662" y="2247" time="16029331.81"/>
      <Point x="653" y="2201" time="16029331.83"/>
      <Point x="643" y="2166" time="16029331.84"/>
      <Point x="637" y="2152" time="16029331.86"/>
      <Point x="632" y="2138" time="16029331.87"/>
      <Point x="632" y="2139" time="16029331.89"/>
      <Point x="633" y="2143" time="16029331.90"/>
      <Point x="638" y="2157" time="16029331.91"/>
      <Point x="646" y="2183" time="16029331.93"/>
      <Point x="656" y="2213" time="16029331.94"/>
      <Point x="665" y="2252" time="16029331.96"/>
      <Point x="674" y="2294" time="16029331.97"/>
      <Point x="680" y="2333" time="16029331.99"/>
      <Point x="685" y="2357" time="16029332.00"/>
    </Stroke>
    <Stroke colour="black" start_time="16029332.27" end_time="16029332.56">
      <Point x="707" y="2301" time="16029332.27"/>
      <Point x="711" y="2306" time="16029332.29"/>
      <Point x="711" y="2317" time="16029332.30"/>
      <Point x="710" y="2333" time="16029332.32"/>
      <Point x="709" y="2354" time="16029332.33"/>
      <Point x="709" y="2366" time="16029332.34"/>
      <Point x="708" y="2378" time="16029332.36"/>
      <Point x="707" y="2377" time="16029332.42"/>
      <Point x="707" y="2374" time="16029332.42"/>
      <Point x="705" y="2369" time="16029332.43"/>
      <Point x="704" y="2353" time="16029332.43"/>
      <Point x="702" y="2328" time="16029332.44"/>
      <Point x="702" y="2308" time="16029332.45"/>
      <Point x="703" y="2288" time="16029332.47"/>
      <Point x="708" y="2280" time="16029332.48"/>
      <Point x="714" y="2273" time="16029332.49"/>
      <Point x="721" y="2275" time="16029332.51"/>
      <Point x="726" y="2271" time="16029332.52"/>
      <Point x="731" y="2272" time="16029332.54"/>
      <Point x="734" y="2273" time="16029332.55"/>
      <Point x="740" y="2278" time="16029332.56"/>
    </Stroke>
    <Stroke colour="black" start_time="16029332.69" end_time="16029332.80">
      <Point x="765" y="2322" time="16029332.69"/>
      <Point x="776" y="2335" time="16029332.70"/>
      <Point x="783" y="2357" time="16029332.72"/>
      <Point x="787" y="2374" time="16029332.73"/>
      <Point x="789" y="2390" time="16029332.75"/>
      <Point x="789" y="2398" time="16029332.76"/>
      <Point x="787" y="2402" time="16029332.78"/>
      <Point x="784" y="2393" time="16029332.79"/>
      <Point x="785" y="2381" time="16029332.80"/>
    </Stroke>
    <Stroke colour="black" start_time="16029332.94" end_time="16029333.00">
      <Point x="762" y="2131" time="16029332.94"/>
      <Point x="770" y="2129" time="16029332.96"/>
      <Point x="773" y="2125" time="16029332.98"/>
      <Point x="774" y="2125" time="16029332.99"/>
      <Point x="774" y="2121" time="16029333.00"/>
    </Stroke>
    <Stroke colour="black" start_time="16029333.29" end_time="16029333.58">
      <Point x="893" y="2300" time="16029333.29"/>
      <Point x="892" y="2297" time="16029333.31"/>
      <Point x="887" y="2288" time="16029333.32"/>
      <Point x="880" y="2287" time="16029333.34"/>
      <Point x="870" y="2287" time="16029333.35"/>
      <Point x="859" y="2293" time="16029333.37"/>
      <Point x="848" y="2296" time="16029333.38"/>
      <Point x="841" y="2311" time="16029333.40"/>
      <Point x="838" y="2327" time="16029333.41"/>
      <Point x="838" y="2340" time="16029333.43"/>
      <Point x="842" y="2356" time="16029333.44"/>
      <Point x="850" y="2369" time="16029333.46"/>
      <Point x="861" y="2381" time="16029333.47"/>
      <Point x="877" y="2396" time="16029333.48"/>
      <Point x="896" y="2398" time="16029333.50"/>
      <Point x="917" y="2399" time="16029333.51"/>
      <Point x="941" y="2404" time="16029333.53"/>
      <Point x="956" y="2401" time="16029333.54"/>
      <Point x="966" y="2394" time="16029333.55"/>
      <Point x="974" y="2391" time="16029333.57"/>
      <Point x="979" y="2383" time="16029333.58"/>
    </Stroke>
    <Stroke colour="black" start_time="16029336.09" end_time="16029336.62">
      <Point x="1232" y="2299" time="16029336.09"/>
      <Point x="1232" y="2295" time="16029336.11"/>
      <Point x="1228" y="2280" time="16029336.12"/>
      <Point x="1223" y="2272" time="16029336.13"/>
      <Point x="1213" y="2260" time="16029336.15"/>
      <Point x="1201" y="2257" time="16029336.17"/>
      <Point x="1185" y="2254" time="16029336.18"/>
      <Point x="1171" y="2258" time="16029336.19"/>
      <Point x="1158" y="2268" time="16029336.21"/>
      <Point x="1148" y="2280" time="16029336.22"/>
      <Point x="1143" y="2296" time="16029336.24"/>
      <Point x="1140" y="2312" time="16029336.25"/>
      <Point x="1141" y="2332" time="16029336.27"/>
      <Point x="1146" y="2352" time="16029336.28"/>
      <Point x="1151" y="2363" time="16029336.29"/>
      <Point x="1160" y="2379" time="16029336.31"/>
      <Point x="1170" y="2386" time="16029336.33"/>
      <Point x="1181" y="2390" time="16029336.34"/>
      <Point x="1190" y="2382" time="16029336.35"/>
      <Point x="1204" y="2369" time="16029336.37"/>
      <Point x="1218" y="2345" time="16029336.38"/>
      <Point x="1228" y="2307" time="16029336.40"/>
      <Point x="1231" y="2259" time="16029336.41"/>
      <Point x="1229" y="2212" time="16029336.43"/>
      <Point x="1225" y="2176" time="16029336.44"/>
      <Point x="1220" y="2147" time="16029336.46"/>
      <Point x="1218" y="2135" time="16029336.47"/>
      <Point x="1218" y="2136" time="16029336.49"/>
      <Point x="1217" y="2132" time="16029336.50"/>
      <Point x="1221" y="2147" time="16029336.51"/>
      <Point x="1228" y="2176" time="16029336.53"/>
      <Point x="1235" y="2207" time="16029336.54"/>
      <Point x="1241" y="2246" time="16029336.56"/>
      <Point x="1248" y="2290" time="16029336.57"/>
      <Point x="1250" y="2322" time="16029336.59"/>
      <Point x="1252" y="2346" time="16029336.60"/>
      <Point x="1249" y="2355" time="16029336.62"/>
    </Stroke>
    <Stroke colour="black" start_time="16029336.83" end_time="16029337.18">
      <Point x="1286" y="2306" time="16029336.83"/>
      <Point x="1297" y="2314" time="16029336.84"/>
      <Point x="1303" y="2314" time="16029336.86"/>
      <Point x="1308" y="2312" time="16029336.88"/>
      <Point x="1312" y="2308" time="16029336.89"/>
      <Point x="1316" y="2296" time="16029336.90"/>
      <Point x="1317" y="2280" time="16029336.92"/>
      <Point x="1317" y="2263" time="16029336.93"/>
      <Point x="1313" y="2248" time="16029336.95"/>
      <Point x="1307" y="2241" time="16029336.96"/>
      <Point x="1300" y="2237" time="16029336.98"/>
      <Point x="1288" y="2234" time="16029336.99"/>
      <Point x="1278" y="2239" time="16029337.01"/>
      <Point x="1272" y="2252" time="16029337.02"/>
      <Point x="1266" y="2265" time="16029337.04"/>
      <Point x="1265" y="2285" time="16029337.05"/>
      <Point x="1269" y="2309" time="16029337.06"/>
      <Point x="1277" y="2332" time="16029337.08"/>
      <Point x="1286" y="2351" time="16029337.09"/>
      <Point x="1300" y="2366" time="16029337.11"/>
      <Point x="1317" y="2376" time="16029337.12"/>
      <Point x="1333" y="2378" time="16029337.14"/>
      <Point x="1348" y="2373" time="16029337.15"/>
      <Point x="1360" y="2363" time="16029337.17"/>
      <Point x="1375" y="2352" time="16029337.18"/>
    </Stroke>
    <Stroke colour="black" start_time="16029337.35" end_time="16029337.47">
      <Point x="1459" y="2169" time="16029337.35"/>
      <Point x="1468" y="2159" time="16029337.37"/>
      <Point x="1471" y="2150" time="16029337.38"/>
      <Point x="1469" y="2139" time="16029337.40"/>
      <Point x="1462" y="2128" time="16029337.41"/>
      <Point x="1442" y="2107" time="16029337.42"/>
      <Point x="1425" y="2098" time="16029337.44"/>
      <Point x="1407" y="2097" time="16029337.46"/>
      <Point x="1392" y="2104" time="16029337.47"/>
    </Stroke>
    <Stroke colour="black" start_time="16029337.50" end_time="16029337.60">
      <Point x="1383" y="2149" time="16029337.50"/>
      <Point x="1387" y="2190" time="16029337.51"/>
      <Point x="1389" y="2229" time="16029337.53"/>
      <Point x="1395" y="2277" time="16029337.54"/>
      <Point x="1399" y="2321" time="16029337.56"/>
      <Point x="1404" y="2365" time="16029337.57"/>
      <Point x="1404" y="2393" time="16029337.58"/>
      <Point x="1399" y="2410" time="16029337.60"/>
    </Stroke>
    <Stroke colour="black" start_time="16029337.80" end_time="16029337.92">
      <Point x="1382" y="2227" time="16029337.80"/>
      <Point x="1382" y="2227" time="16029337.82"/>
      <Point x="1382" y="2227" time="16029337.84"/>
      <Point x="1381" y="2227" time="16029337.85"/>
      <Point x="1374" y="2228" time="16029337.86"/>
      <Point x="1363" y="2225" time="16029337.88"/>
      <Point x="1352" y="2223" time="16029337.89"/>
      <Point x="1346" y="2224" time="16029337.91"/>
      <Point x="1343" y="2228" time="16029337.92"/>
    </Stroke>
    <Stroke colour="black" start_time="16029338.15" end_time="16029338.44">
      <Point x="1438" y="2299" time="16029338.15"/>
      <Point x="1446" y="2301" time="16029338.17"/>
      <Point x="1451" y="2301" time="16029338.18"/>
      <Point x="1456" y="2296" time="16029338.20"/>
      <Point x="1459" y="2287" time="16029338.21"/>
      <Point x="1459" y="2271" time="16029338.23"/>
      <Point x="1457" y="2255" time="16029338.24"/>
      <Point x="1450" y="2240" time="16029338.26"/>
      <Point x="1446" y="2236" time="16029338.27"/>
      <Point x="1440" y="2238" time="16029338.28"/>
      <Point x="1435" y="2243" time="16029338.30"/>
      <Point x="1430" y="2251" time="16029338.31"/>
      <Point x="1425" y="2265" time="16029338.33"/>
      <Point x="1423" y="2281" time="16029338.34"/>
      <Point x="1421" y="2301" time="16029338.35"/>
      <Point x="1421" y="2322" time="16029338.37"/>
      <Point x="1428" y="2345" time="16029338.39"/>
      <Point x="1433" y="2356" time="16029338.40"/>
      <Point x="1441" y="2367" time="16029338.41"/>
      <Point x="1453" y="2374" time="16029338.43"/>
      <Point x="1465" y="2376" time="16029338.44"/>
    </Stroke>
    <Stroke colour="black" start_time="16029338.59" end_time="16029338.95">
      <Point x="1515" y="2251" time="16029338.59"/>
      <Point x="1518" y="2263" time="16029338.61"/>
      <Point x="1519" y="2275" time="16029338.63"/>
      <Point x="1516" y="2288" time="16029338.64"/>
      <Point x="1516" y="2309" time="16029338.65"/>
      <Point x="1515" y="2325" time="16029338.67"/>
      <Point x="1514" y="2338" time="16029338.68"/>
      <Point x="1515" y="2346" time="16029338.70"/>
      <Point x="1514" y="2345" time="16029338.71"/>
      <Point x="1515" y="2345" time="16029338.73"/>
      <Point x="1518" y="2337" time="16029338.74"/>
      <Point x="1523" y="2315" time="16029338.76"/>
      <Point x="1528" y="2290" time="16029338.77"/>
      <Point x="1534" y="2268" time="16029338.79"/>
      <Point x="1544" y="2253" time="16029338.80"/>
      <Point x="1554" y="2251" time="16029338.81"/>
      <Point x="1564" y="2253" time="16029338.83"/>
      <Point x="1575" y="2263" time="16029338.85"/>
      <Point x="1582" y="2278" time="16029338.86"/>
      <Point x="1590" y="2301" time="16029338.87"/>
      <Point x="1591" y="2321" time="16029338.89"/>
      <Point x="1594" y="2340" time="16029338.90"/>
      <Point x="1595" y="2353" time="16029338.92"/>
      <Point x="1595" y="2357" time="16029338.93"/>
      <Point x="1594" y="2353" time="16029338.95"/>
    </Stroke>
    <Stroke colour="black" start_time="16029339.11" end_time="16029339.17">
      <Point x="1675" y="2262" time="16029339.11"/>
      <Point x="1676" y="2261" time="16029339.13"/>
      <Point x="1675" y="2262" time="16029339.15"/>
      <Point x="1668" y="2263" time="16029339.16"/>
      <Point x="1661" y="2270" time="16029339.17"/>
    </Stroke>
    <Stroke colour="black" start_time="16029339.23" end_time="16029339.45">
      <Point x="1640" y="2309" time="16029339.23"/>
      <Point x="1640" y="2321" time="16029339.24"/>
      <Point x="1643" y="2328" time="16029339.26"/>
      <Point x="1650" y="2344" time="16029339.28"/>
      <Point x="1657" y="2358" time="16029339.29"/>
      <Point x="1664" y="2372" time="16029339.31"/>
      <Point x="1667" y="2384" time="16029339.32"/>
      <Point x="1672" y="2400" time="16029339.34"/>
      <Point x="1674" y="2412" time="16029339.35"/>
      <Point x="1671" y="2412" time="16029339.37"/>
      <Point x="1667" y="2413" time="16029339.38"/>
      <Point x="1659" y="2411" time="16029339.39"/>
      <Point x="1650" y="2405" time="16029339.41"/>
      <Point x="1640" y="2396" time="16029339.42"/>
      <Point x="1631" y="2381" time="16029339.44"/>
      <Point x="1626" y="2366" time="16029339.45"/>
    </Stroke>
    <Stroke colour="black" start_time="16029339.63" end_time="16029339.75">
      <Point x="1720" y="2265" time="16029339.63"/>
      <Point x="1731" y="2287" time="16029339.65"/>
      <Point x="1733" y="2311" time="16029339.66"/>
      <Point x="1734" y="2332" time="16029339.68"/>
      <Point x="1732" y="2349" time="16029339.70"/>
      <Point x="1725" y="2355" time="16029339.71"/>
      <Point x="1720" y="2361" time="16029339.72"/>
      <Point x="1718" y="2362" time="16029339.74"/>
      <Point x="1714" y="2350" time="16029339.75"/>
    </Stroke>
    <Stroke colour="black" start_time="16029339.86" end_time="16029339.98">
      <Point x="1722" y="2135" time="16029339.86"/>
      <Point x="1726" y="2121" time="16029339.88"/>
      <Point x="1727" y="2108" time="16029339.89"/>
      <Point x="1728" y="2099" time="16029339.90"/>
      <Point x="1730" y="2094" time="16029339.92"/>
      <Point x="1730" y="2090" time="16029339.94"/>
      <Point x="1727" y="2091" time="16029339.95"/>
      <Point x="1730" y="2099" time="16029339.96"/>
      <Point x="1728" y="2107" time="16029339.98"/>
    </Stroke>
    <Stroke colour="black" start_time="16029342.36" end_time="16029342.59">
      <Point x="1790" y="2281" time="16029342.36"/>
      <Point x="1796" y="2304" time="16029342.38"/>
      <Point x="1800" y="2323" time="16029342.39"/>
      <Point x="1804" y="2343" time="16029342.40"/>
      <Point x="1809" y="2358" time="16029342.42"/>
      <Point x="1813" y="2366" time="16029342.43"/>
      <Point x="1814" y="2365" time="16029342.45"/>
      <Point x="1815" y="2361" time="16029342.46"/>
      <Point x="1821" y="2346" time="16029342.47"/>
      <Point x="1832" y="2326" time="16029342.49"/>
      <Point x="1841" y="2297" time="16029342.51"/>
      <Point x="1852" y="2272" time="16029342.52"/>
      <Point x="1864" y="2254" time="16029342.53"/>
      <Point x="1871" y="2239" time="16029342.55"/>
      <Point x="1879" y="2231" time="16029342.56"/>
      <Point x="1881" y="2222" time="16029342.58"/>
      <Point x="1886" y="2220" time="16029342.59"/>
    </Stroke>
    <Stroke colour="black" start_time="16029342.78" end_time="16029343.19">
      <Point x="1895" y="2289" time="16029342.78"/>
      <Point x="1900" y="2287" time="16029342.80"/>
      <Point x="1905" y="2285" time="16029342.82"/>
      <Point x="1911" y="2284" time="16029342.83"/>
      <Point x="1914" y="2277" time="16029342.85"/>
      <Point x="1923" y="2274" time="16029342.86"/>
      <Point x="1929" y="2263" time="16029342.87"/>
      <Point x="1937" y="2251" time="16029342.89"/>
      <Point x="1936" y="2234" time="16029342.90"/>
      <Point x="1936" y="2226" time="16029342.91"/>
      <Point x="1934" y="2222" time="16029342.93"/>
      <Point x="1925" y="2217" time="16029342.95"/>
      <Point x="1915" y="2221" time="16029342.96"/>
      <Point x="1903" y="2227" time="16029342.97"/>
      <Point x="1892" y="2234" time="16029342.99"/>
      <Point x="1880" y="2239" time="16029343.00"/>
      <Point x="1876" y="2253" time="16029343.02"/>
      <Point x="1874" y="2268" time="16029343.03"/>
      <Point x="1874" y="2280" time="16029343.05"/>
      <Point x="1886" y="2301" time="16029343.06"/>
      <Point x="1899" y="2318" time="16029343.08"/>
      <Point x="1908" y="2328" time="16029343.09"/>
      <Point x="1920" y="2340" time="16029343.11"/>
      <Point x="1932" y="2348" time="16029343.12"/>
      <Point x="1940" y="2350" time="16029343.13"/>
      <Point x="1947" y="2350" time="16029343.15"/>
      <Point x="1956" y="2343" time="16029343.17"/>
      <Point x="1961" y="2328" time="16029343.18"/>
      <Point x="1967" y="2308" time="16029343.19"/>
    </Stroke>
    <Stroke colour="black" start_time="16029343.34" end_time="16029343.52">
      <Point x="1983" y="2135" time="16029343.34"/>
      <Point x="1985" y="2138" time="16029343.36"/>
      <Point x="1985" y="2142" time="16029343.37"/>
      <Point x="1986" y="2160" time="16029343.39"/>
      <Point x="1987" y="2182" time="16029343.40"/>
      <Point x="1990" y="2211" time="16029343.42"/>
      <Point x="1998" y="2247" time="16029343.43"/>
      <Point x="2004" y="2280" time="16029343.45"/>
      <Point x="2010" y="2312" time="16029343.46"/>
      <Point x="2014" y="2336" time="16029343.47"/>
      <Point x="2016" y="2352" time="16029343.49"/>
      <Point x="2016" y="2357" time="16029343.50"/>
      <Point x="2019" y="2359" time="16029343.52"/>
    </Stroke>
    <Stroke colour="black" start_time="16029343.70" end_time="16029343.82">
      <Point x="2029" y="2260" time="16029343.70"/>
      <Point x="2031" y="2263" time="16029343.71"/>
      <Point x="2035" y="2270" time="16029343.73"/>
      <Point x="2037" y="2277" time="16029343.74"/>
      <Point x="2046" y="2292" time="16029343.76"/>
      <Point x="2053" y="2305" time="16029343.77"/>
      <Point x="2058" y="2312" time="16029343.79"/>
      <Point x="2060" y="2315" time="16029343.80"/>
      <Point x="2065" y="2318" time="16029343.82"/>
    </Stroke>
    <Stroke colour="black" start_time="16029343.97" end_time="16029344.15">
      <Point x="2121" y="2234" time="16029343.97"/>
      <Point x="2125" y="2241" time="16029343.99"/>
      <Point x="2121" y="2251" time="16029344.00"/>
      <Point x="2114" y="2268" time="16029344.02"/>
      <Point x="2107" y="2294" time="16029344.03"/>
      <Point x="2097" y="2325" time="16029344.05"/>
      <Point x="2085" y="2361" time="16029344.06"/>
      <Point x="2077" y="2400" time="16029344.08"/>
      <Point x="2068" y="2434" time="16029344.09"/>
      <Point x="2060" y="2451" time="16029344.10"/>
      <Point x="2058" y="2466" time="16029344.12"/>
      <Point x="2058" y="2469" time="16029344.13"/>
      <Point x="2056" y="2470" time="16029344.15"/>
    </Stroke>
    <Stroke colour="black" start_time="16029345.45" end_time="16029345.58">
      <Point x="2160" y="2307" time="16029345.45"/>
      <Point x="2162" y="2307" time="16029345.47"/>
      <Point x="2165" y="2309" time="16029345.49"/>
      <Point x="2162" y="2306" time="16029345.50"/>
      <Point x="2164" y="2310" time="16029345.52"/>
      <Point x="2162" y="2307" time="16029345.53"/>
      <Point x="2155" y="2305" time="16029345.55"/>
      <Point x="2152" y="2307" time="16029345.56"/>
      <Point x="2152" y="2307" time="16029345.58"/>
    </Stroke>
    <Stroke colour="black" start_time="16029348.90" end_time="16029349.02">
      <Point x="2350" y="1956" time="16029348.90"/>
      <Point x="2350" y="1956" time="16029348.91"/>
      <Point x="2348" y="1962" time="16029348.93"/>
      <Point x="2348" y="1976" time="16029348.94"/>
      <Point x="2354" y="1997" time="16029348.96"/>
      <Point x="2356" y="2015" time="16029348.97"/>
      <Point x="2359" y="2032" time="16029348.99"/>
      <Point x="2361" y="2046" time="16029349.00"/>
      <Point x="2364" y="2053" time="16029349.02"/>
    </Stroke>
    <Stroke colour="black" start_time="16029349.21" end_time="16029349.33">
      <Point x="2391" y="1947" time="16029349.21"/>
      <Point x="2397" y="1952" time="16029349.23"/>
      <Point x="2401" y="1959" time="16029349.24"/>
      <Point x="2401" y="1973" time="16029349.26"/>
      <Point x="2404" y="1995" time="16029349.27"/>
      <Point x="2405" y="2014" time="16029349.29"/>
      <Point x="2408" y="2032" time="16029349.30"/>
      <Point x="2412" y="2043" time="16029349.32"/>
      <Point x="2422" y="2053" time="16029349.33"/>
    </Stroke>
    <Stroke colour="black" start_time="16029350.64" end_time="16029350.82">
      <Point x="2543" y="2011" time="16029350.64"/>
      <Point x="2543" y="2011" time="16029350.66"/>
      <Point x="2546" y="2019" time="16029350.67"/>
      <Point x="2543" y="2031" time="16029350.68"/>
      <Point x="2540" y="2054" time="16029350.70"/>
      <Point x="2540" y="2084" time="16029350.72"/>
      <Point x="2540" y="2119" time="16029350.73"/>
      <Point x="2544" y="2157" time="16029350.75"/>
      <Point x="2552" y="2195" time="16029350.76"/>
      <Point x="2557" y="2226" time="16029350.77"/>
      <Point x="2557" y="2246" time="16029350.79"/>
      <Point x="2560" y="2263" time="16029350.81"/>
      <Point x="2562" y="2276" time="16029350.82"/>
    </Stroke>
    <Stroke colour="black" start_time="16029351.22" end_time="16029351.63">
      <Point x="2732" y="2014" time="16029351.22"/>
      <Point x="2736" y="2016" time="16029351.24"/>
      <Point x="2736" y="2016" time="16029351.26"/>
      <Point x="2734" y="2023" time="16029351.27"/>
      <Point x="2736" y="2043" time="16029351.28"/>
      <Point x="2735" y="2070" time="16029351.30"/>
      <Point x="2736" y="2106" time="16029351.31"/>
      <Point x="2736" y="2143" time="16029351.32"/>
      <Point x="2741" y="2185" time="16029351.34"/>
      <Point x="2746" y="2222" time="16029351.36"/>
      <Point x="2743" y="2246" time="16029351.37"/>
      <Point x="2746" y="2263" time="16029351.38"/>
      <Point x="2741" y="2263" time="16029351.40"/>
      <Point x="2744" y="2265" time="16029351.42"/>
      <Point x="2745" y="2254" time="16029351.43"/>
      <Point x="2752" y="2233" time="16029351.44"/>
      <Point x="2757" y="2208" time="16029351.46"/>
      <Point x="2762" y="2183" time="16029351.47"/>
      <Point x="2775" y="2167" time="16029351.48"/>
      <Point x="2786" y="2158" time="16029351.50"/>
      <Point x="2799" y="2157" time="16029351.52"/>
      <Point x="2808" y="2159" time="16029351.53"/>
      <Point x="2820" y="2171" time="16029351.54"/>
      <Point x="2829" y="2190" time="16029351.56"/>
      <Point x="2836" y="2215" time="16029351.58"/>
      <Point x="2840" y="2239" time="16029351.59"/>
      <Point x="2843" y="2256" time="16029351.60"/>
      <Point x="2844" y="2266" time="16029351.62"/>
      <Point x="2848" y="2268" time="16029351.63"/>
    </Stroke>
    <Stroke colour="black" start_time="16029351.79" end_time="16029352.20">
      <Point x="2955" y="2200" time="16029351.79"/>
      <Point x="2960" y="2196" time="16029351.81"/>
      <Point x="2961" y="2189" time="16029351.82"/>
      <Point x="2963" y="2181" time="16029351.84"/>
      <Point x="2956" y="2171" time="16029351.85"/>
      <Point x="2946" y="2164" time="16029351.87"/>
      <Point x="2930" y="2158" time="16029351.88"/>
      <Point x="2919" y="2157" time="16029351.90"/>
      <Point x="2910" y="2160" time="16029351.91"/>
      <Point x="2904" y="2166" time="16029351.93"/>
      <Point x="2896" y="2172" time="16029351.94"/>
      <Point x="2897" y="2188" time="16029351.96"/>
      <Point x="2893" y="2202" time="16029351.97"/>
      <Point x="2897" y="2220" time="16029351.98"/>
      <Point x="2894" y="2234" time="16029352.00"/>
      <Point x="2900" y="2249" time="16029352.02"/>
      <Point x="2906" y="2260" time="16029352.03"/>
      <Point x="2912" y="2265" time="16029352.04"/>
      <Point x="2929" y="2267" time="16029352.06"/>
      <Point x="2949" y="2259" time="16029352.07"/>
      <Point x="2963" y="2241" time="16029352.09"/>
      <Point x="2975" y="2231" time="16029352.10"/>
      <Point x="2982" y="2219" time="16029352.12"/>
      <Point x="2980" y="2205" time="16029352.13"/>
      <Point x="2975" y="2193" time="16029352.14"/>
      <Point x="2967" y="2183" time="16029352.16"/>
      <Point x="2965" y="2180" time="16029352.17"/>
      <Point x="2962" y="2177" time="16029352.19"/>
      <Point x="2961" y="2178" time="16029352.20"/>
    </Stroke>
    <Stroke colour="black" start_time="16029352.36" end_time="16029352.83">
      <Point x="3030" y="2195" time="16029352.36"/>
      <Point x="3034" y="2197" time="16029352.38"/>
      <Point x="3032" y="2199" time="16029352.40"/>
      <Point x="3033" y="2215" time="16029352.42"/>
      <Point x="3030" y="2234" time="16029352.43"/>
      <Point x="3029" y="2263" time="16029352.44"/>
      <Point x="3028" y="2301" time="16029352.46"/>
      <Point x="3021" y="2340" time="16029352.47"/>
      <Point x="3021" y="2383" time="16029352.49"/>
      <Point x="3018" y="2417" time="16029352.50"/>
      <Point x="3017" y="2434" time="16029352.52"/>
      <Point x="3018" y="2434" time="16029352.53"/>
      <Point x="3013" y="2427" time="16029352.54"/>
      <Point x="3008" y="2405" time="16029352.56"/>
      <Point x="3001" y="2368" time="16029352.57"/>
      <Point x="3003" y="2330" time="16029352.59"/>
      <Point x="3003" y="2286" time="16029352.60"/>
      <Point x="3010" y="2253" time="16029352.62"/>
      <Point x="3014" y="2221" time="16029352.63"/>
      <Point x="3023" y="2197" time="16029352.64"/>
      <Point x="3030" y="2178" time="16029352.66"/>
      <Point x="3033" y="2169" time="16029352.67"/>
      <Point x="3045" y="2171" time="16029352.69"/>
      <Point x="3053" y="2174" time="16029352.70"/>
      <Point x="3067" y="2188" time="16029352.71"/>
      <Point x="3072" y="2205" time="16029352.73"/>
      <Point x="3079" y="2231" time="16029352.75"/>
      <Point x="3076" y="2251" time="16029352.76"/>
      <Point x="3076" y="2268" time="16029352.77"/>
      <Point x="3066" y="2272" time="16029352.79"/>
      <Point x="3057" y="2274" time="16029352.80"/>
      <Point x="3040" y="2268" time="16029352.82"/>
      <Point x="3030" y="2262" time="16029352.83"/>
    </Stroke>
    <Stroke colour="black" start_time="16029353.05" end_time="16029353.41">
      <Point x="3133" y="2235" time="16029353.05"/>
      <Point x="3144" y="2236" time="16029353.07"/>
      <Point x="3149" y="2236" time="16029353.09"/>
      <Point x="3153" y="2231" time="16029353.10"/>
      <Point x="3158" y="2227" time="16029353.11"/>
      <Point x="3163" y="2217" time="16029353.13"/>
      <Point x="3164" y="2204" time="16029353.14"/>
      <Point x="3162" y="2193" time="16029353.16"/>
      <Point x="3159" y="2185" time="16029353.17"/>
      <Point x="3153" y="2179" time="16029353.19"/>
      <Point x="3148" y="2178" time="16029353.20"/>
      <Point x="3139" y="2177" time="16029353.21"/>
      <Point x="3132" y="2180" time="16029353.23"/>
      <Point x="3126" y="2186" time="16029353.25"/>
      <Point x="3119" y="2192" time="16029353.26"/>
      <Point x="3119" y="2203" time="16029353.27"/>
      <Point x="3119" y="2215" time="16029353.29"/>
      <Point x="3119" y="2226" time="16029353.30"/>
      <Point x="3125" y="2237" time="16029353.32"/>
      <Point x="3132" y="2247" time="16029353.33"/>
      <Point x="3141" y="2256" time="16029353.35"/>
      <Point x="3153" y="2260" time="16029353.36"/>
      <Point x="3167" y="2263" time="16029353.38"/>
      <Point x="3181" y="2260" time="16029353.39"/>
      <Point x="3196" y="2257" time="16029353.41"/>
    </Stroke>
    <Stroke colour="black" start_time="16029353.60" end_time="16029354.18">
      <Point x="3275" y="2196" time="16029353.60"/>
      <Point x="3288" y="2200" time="16029353.62"/>
      <Point x="3288" y="2200" time="16029353.63"/>
      <Point x="3288" y="2200" time="16029353.65"/>
      <Point x="3285" y="2198" time="16029353.66"/>
      <Point x="3275" y="2185" time="16029353.67"/>
      <Point x="3267" y="2176" time="16029353.69"/>
      <Point x="3259" y="2167" time="16029353.70"/>
      <Point x="3248" y="2161" time="16029353.72"/>
      <Point x="3239" y="2159" time="16029353.73"/>
      <Point x="3232" y="2162" time="16029353.75"/>
      <Point x="3229" y="2170" time="16029353.76"/>
      <Point x="3226" y="2179" time="16029353.78"/>
      <Point x="3225" y="2191" time="16029353.79"/>
      <Point x="3224" y="2205" time="16029353.80"/>
      <Point x="3222" y="2218" time="16029353.82"/>
      <Point x="3224" y="2233" time="16029353.83"/>
      <Point x="3227" y="2247" time="16029353.85"/>
      <Point x="3232" y="2259" time="16029353.86"/>
      <Point x="3241" y="2267" time="16029353.88"/>
      <Point x="3246" y="2268" time="16029353.89"/>
      <Point x="3253" y="2260" time="16029353.90"/>
      <Point x="3264" y="2244" time="16029353.92"/>
      <Point x="3274" y="2216" time="16029353.94"/>
      <Point x="3284" y="2182" time="16029353.95"/>
      <Point x="3281" y="2142" time="16029353.96"/>
      <Point x="3280" y="2108" time="16029353.98"/>
      <Point x="3276" y="2082" time="16029353.99"/>
      <Point x="3270" y="2064" time="16029354.01"/>
      <Point x="3269" y="2060" time="16029354.02"/>
      <Point x="3275" y="2065" time="16029354.04"/>
      <Point x="3276" y="2076" time="16029354.05"/>
      <Point x="3279" y="2098" time="16029354.06"/>
      <Point x="3287" y="2130" time="16029354.08"/>
      <Point x="3291" y="2167" time="16029354.10"/>
      <Point x="3297" y="2208" time="16029354.11"/>
      <Point x="3303" y="2244" time="16029354.12"/>
      <Point x="3305" y="2263" time="16029354.14"/>
      <Point x="3310" y="2277" time="16029354.15"/>
      <Point x="3308" y="2280" time="16029354.17"/>
      <Point x="3317" y="2275" time="16029354.18"/>
    </Stroke>
    <Stroke colour="black" start_time="16029356.17" end_time="16029356.41">
      <Point x="3544" y="2011" time="16029356.17"/>
      <Point x="3549" y="2012" time="16029356.19"/>
      <Point x="3551" y="2014" time="16029356.20"/>
      <Point x="3548" y="2019" time="16029356.22"/>
      <Point x="3544" y="2037" time="16029356.23"/>
      <Point x="3541" y="2062" time="16029356.25"/>
      <Point x="3539" y="2091" time="16029356.26"/>
      <Point x="3541" y="2127" time="16029356.28"/>
      <Point x="3549" y="2167" time="16029356.29"/>
      <Point x="3553" y="2201" time="16029356.31"/>
      <Point x="3555" y="2229" time="16029356.32"/>
      <Point x="3559" y="2250" time="16029356.33"/>
      <Point x="3556" y="2259" time="16029356.35"/>
      <Point x="3556" y="2266" time="16029356.36"/>
      <Point x="3554" y="2268" time="16029356.38"/>
      <Point x="3551" y="2265" time="16029356.41"/>
      <Point x="3558" y="2257" time="16029356.41"/>
    </Stroke>
    <Stroke colour="black" start_time="16029356.52" end_time="16029356.64">
      <Point x="3576" y="2147" time="16029356.52"/>
      <Point x="3583" y="2150" time="16029356.55"/>
      <Point x="3583" y="2150" time="16029356.56"/>
      <Point x="3578" y="2150" time="16029356.57"/>
      <Point x="3568" y="2151" time="16029356.58"/>
      <Point x="3551" y="2152" time="16029356.60"/>
      <Point x="3538" y="2155" time="16029356.61"/>
      <Point x="3533" y="2162" time="16029356.63"/>
      <Point x="3530" y="2166" time="16029356.64"/>
    </Stroke>
    <Stroke colour="black" start_time="16029356.84" end_time="16029357.25">
      <Point x="3603" y="2019" time="16029356.84"/>
      <Point x="3613" y="2018" time="16029356.86"/>
      <Point x="3614" y="2017" time="16029356.88"/>
      <Point x="3619" y="2025" time="16029356.89"/>
      <Point x="3626" y="2042" time="16029356.91"/>
      <Point x="3629" y="2064" time="16029356.92"/>
      <Point x="3632" y="2094" time="16029356.93"/>
      <Point x="3633" y="2125" time="16029356.95"/>
      <Point x="3634" y="2157" time="16029356.96"/>
      <Point x="3636" y="2186" time="16029356.98"/>
      <Point x="3638" y="2209" time="16029356.99"/>
      <Point x="3636" y="2219" time="16029357.01"/>
      <Point x="3634" y="2222" time="16029357.02"/>
      <Point x="3638" y="2222" time="16029357.04"/>
      <Point x="3636" y="2213" time="16029357.05"/>
      <Point x="3644" y="2196" time="16029357.07"/>
      <Point x="3646" y="2173" time="16029357.08"/>
      <Point x="3654" y="2157" time="16029357.10"/>
      <Point x="3665" y="2149" time="16029357.11"/>
      <Point x="3676" y="2149" time="16029357.12"/>
      <Point x="3687" y="2153" time="16029357.14"/>
      <Point x="3698" y="2165" time="16029357.15"/>
      <Point x="3701" y="2181" time="16029357.17"/>
      <Point x="3705" y="2202" time="16029357.18"/>
      <Point x="3713" y="2225" time="16029357.20"/>
      <Point x="3717" y="2245" time="16029357.21"/>
      <Point x="3719" y="2256" time="16029357.23"/>
      <Point x="3721" y="2259" time="16029357.24"/>
      <Point x="3723" y="2257" time="16029357.25"/>
    </Stroke>
    <Stroke colour="black" start_time="16029357.40" end_time="16029357.52">
      <Point x="3768" y="2193" time="16029357.40"/>
      <Point x="3780" y="2196" time="16029357.42"/>
      <Point x="3793" y="2199" time="16029357.43"/>
      <Point x="3798" y="2199" time="16029357.45"/>
      <Point x="3805" y="2197" time="16029357.46"/>
      <Point x="3814" y="2192" time="16029357.48"/>
      <Point x="3817" y="2181" time="16029357.49"/>
      <Point x="3814" y="2170" time="16029357.51"/>
      <Point x="3812" y="2166" time="16029357.52"/>
    </Stroke>
    <Stroke colour="black" start_time="16029357.55" end_time="16029357.77">
      <Point x="3804" y="2164" time="16029357.55"/>
      <Point x="3798" y="2166" time="16029357.56"/>
      <Point x="3790" y="2169" time="16029357.58"/>
      <Point x="3783" y="2172" time="16029357.59"/>
      <Point x="3778" y="2178" time="16029357.61"/>
      <Point x="3773" y="2186" time="16029357.62"/>
      <Point x="3771" y="2195" time="16029357.63"/>
      <Point x="3771" y="2207" time="16029357.65"/>
      <Point x="3773" y="2218" time="16029357.67"/>
      <Point x="3781" y="2229" time="16029357.68"/>
      <Point x="3781" y="2235" time="16029357.69"/>
      <Point x="3793" y="2245" time="16029357.71"/>
      <Point x="3801" y="2248" time="16029357.72"/>
      <Point x="3814" y="2251" time="16029357.74"/>
      <Point x="3825" y="2250" time="16029357.75"/>
      <Point x="3841" y="2248" time="16029357.77"/>
    </Stroke>
    <Stroke colour="black" start_time="16029357.95" end_time="16029358.54">
      <Point x="3945" y="2132" time="16029357.95"/>
      <Point x="3948" y="2134" time="16029357.97"/>
      <Point x="3948" y="2134" time="16029357.98"/>
      <Point x="3949" y="2140" time="16029358.00"/>
      <Point x="3946" y="2150" time="16029358.02"/>
      <Point x="3944" y="2168" time="16029358.03"/>
      <Point x="3945" y="2194" time="16029358.04"/>
      <Point x="3942" y="2224" time="16029358.06"/>
      <Point x="3944" y="2264" time="16029358.07"/>
      <Point x="3945" y="2303" time="16029358.09"/>
      <Point x="3947" y="2340" time="16029358.10"/>
      <Point x="3950" y="2370" time="16029358.12"/>
      <Point x="3951" y="2394" time="16029358.13"/>
      <Point x="3947" y="2405" time="16029358.15"/>
      <Point x="3945" y="2408" time="16029358.16"/>
      <Point x="3950" y="2410" time="16029358.18"/>
      <Point x="3947" y="2405" time="16029358.19"/>
      <Point x="3942" y="2391" time="16029358.21"/>
      <Point x="3941" y="2367" time="16029358.22"/>
      <Point x="3945" y="2336" time="16029358.23"/>
      <Point x="3945" y="2297" time="16029358.25"/>
      <Point x="3940" y="2255" time="16029358.26"/>
      <Point x="3945" y="2222" time="16029358.28"/>
      <Point x="3943" y="2190" time="16029358.29"/>
      <Point x="3948" y="2169" time="16029358.30"/>
      <Point x="3953" y="2154" time="16029358.32"/>
      <Point x="3966" y="2150" time="16029358.34"/>
      <Point x="3974" y="2145" time="16029358.35"/>
      <Point x="3988" y="2146" time="16029358.36"/>
      <Point x="4000" y="2150" time="16029358.38"/>
      <Point x="4005" y="2157" time="16029358.39"/>
      <Point x="4010" y="2171" time="16029358.41"/>
      <Point x="4007" y="2189" time="16029358.42"/>
      <Point x="4007" y="2210" time="16029358.44"/>
      <Point x="4000" y="2226" time="16029358.45"/>
      <Point x="3999" y="2236" time="16029358.46"/>
      <Point x="3988" y="2236" time="16029358.48"/>
      <Point x="3981" y="2234" time="16029358.50"/>
      <Point x="3971" y="2225" time="16029358.51"/>
      <Point x="3965" y="2215" time="16029358.52"/>
      <Point x="3969" y="2202" time="16029358.54"/>
    </Stroke>
    <Stroke colour="black" start_time="16029358.90" end_time="16029359.25">
      <Point x="4101" y="2158" time="16029358.90"/>
      <Point x="4101" y="2157" time="16029358.91"/>
      <Point x="4101" y="2157" time="16029358.93"/>
      <Point x="4101" y="2157" time="16029358.94"/>
      <Point x="4102" y="2155" time="16029358.96"/>
      <Point x="4093" y="2147" time="16029358.97"/>
      <Point x="4082" y="2141" time="16029358.99"/>
      <Point x="4070" y="2137" time="16029359.00"/>
      <Point x="4063" y="2142" time="16029359.02"/>
      <Point x="4054" y="2148" time="16029359.03"/>
      <Point x="4047" y="2159" time="16029359.04"/>
      <Point x="4046" y="2175" time="16029359.06"/>
      <Point x="4044" y="2192" time="16029359.07"/>
      <Point x="4044" y="2207" time="16029359.09"/>
      <Point x="4048" y="2222" time="16029359.10"/>
      <Point x="4061" y="2238" time="16029359.12"/>
      <Point x="4070" y="2245" time="16029359.13"/>
      <Point x="4077" y="2243" time="16029359.15"/>
      <Point x="4092" y="2234" time="16029359.16"/>
      <Point x="4100" y="2217" time="16029359.17"/>
      <Point x="4106" y="2199" time="16029359.19"/>
      <Point x="4106" y="2185" time="16029359.20"/>
      <Point x="4104" y="2174" time="16029359.22"/>
      <Point x="4099" y="2166" time="16029359.23"/>
      <Point x="4097" y="2163" time="16029359.25"/>
    </Stroke>
    <Stroke colour="black" start_time="16029359.44" end_time="16029359.61">
      <Point x="4155" y="2010" time="16029359.44"/>
      <Point x="4158" y="2013" time="16029359.46"/>
      <Point x="4164" y="2026" time="16029359.47"/>
      <Point x="4163" y="2045" time="16029359.48"/>
      <Point x="4159" y="2073" time="16029359.50"/>
      <Point x="4160" y="2110" time="16029359.51"/>
      <Point x="4164" y="2148" time="16029359.53"/>
      <Point x="4166" y="2182" time="16029359.54"/>
      <Point x="4168" y="2208" time="16029359.55"/>
      <Point x="4170" y="2226" time="16029359.57"/>
      <Point x="4169" y="2235" time="16029359.59"/>
      <Point x="4172" y="2238" time="16029359.60"/>
      <Point x="4169" y="2235" time="16029359.61"/>
    </Stroke>
    <Stroke colour="black" start_time="16029359.75" end_time="16029359.81">
      <Point x="4188" y="2155" time="16029359.75"/>
      <Point x="4198" y="2177" time="16029359.76"/>
      <Point x="4201" y="2200" time="16029359.78"/>
      <Point x="4199" y="2219" time="16029359.79"/>
      <Point x="4198" y="2234" time="16029359.81"/>
    </Stroke>
    <Stroke colour="black" start_time="16029359.98" end_time="16029360.04">
      <Point x="4184" y="2003" time="16029359.98"/>
      <Point x="4192" y="2003" time="16029359.99"/>
      <Point x="4189" y="2000" time="16029360.01"/>
      <Point x="4189" y="2000" time="16029360.03"/>
      <Point x="4186" y="1998" time="16029360.04"/>
    </Stroke>
    <Stroke colour="black" start_time="16029360.31" end_time="16029360.54">
      <Point x="4268" y="2156" time="16029360.31"/>
      <Point x="4274" y="2154" time="16029360.32"/>
      <Point x="4273" y="2149" time="16029360.34"/>
      <Point x="4266" y="2145" time="16029360.35"/>
      <Point x="4260" y="2146" time="16029360.37"/>
      <Point x="4249" y="2148" time="16029360.39"/>
      <Point x="4245" y="2155" time="16029360.40"/>
      <Point x="4238" y="2165" time="16029360.41"/>
      <Point x="4232" y="2175" time="16029360.43"/>
      <Point x="4234" y="2187" time="16029360.44"/>
      <Point x="4242" y="2198" time="16029360.45"/>
      <Point x="4245" y="2207" time="16029360.47"/>
      <Point x="4256" y="2219" time="16029360.48"/>
      <Point x="4265" y="2227" time="16029360.50"/>
      <Point x="4276" y="2233" time="16029360.51"/>
      <Point x="4285" y="2234" time="16029360.53"/>
      <Point x="4295" y="2232" time="16029360.54"/>
    </Stroke>
    <Stroke colour="black" start_time="16029360.70" end_time="16029361.05">
      <Point x="4327" y="2166" time="16029360.70"/>
      <Point x="4331" y="2169" time="16029360.71"/>
      <Point x="4331" y="2168" time="16029360.73"/>
      <Point x="4339" y="2170" time="16029360.74"/>
      <Point x="4341" y="2166" time="16029360.76"/>
      <Point x="4348" y="2157" time="16029360.77"/>
      <Point x="4355" y="2144" time="16029360.80"/>
      <Point x="4359" y="2130" time="16029360.80"/>
      <Point x="4364" y="2121" time="16029360.82"/>
      <Point x="4362" y="2118" time="16029360.83"/>
      <Point x="4354" y="2116" time="16029360.84"/>
      <Point x="4350" y="2121" time="16029360.86"/>
      <Point x="4337" y="2127" time="16029360.87"/>
      <Point x="4326" y="2138" time="16029360.89"/>
      <Point x="4319" y="2151" time="16029360.90"/>
      <Point x="4309" y="2180" time="16029360.93"/>
      <Point x="4307" y="2193" time="16029360.95"/>
      <Point x="4309" y="2205" time="16029360.96"/>
      <Point x="4312" y="2214" time="16029360.98"/>
      <Point x="4316" y="2221" time="16029360.99"/>
      <Point x="4331" y="2229" time="16029361.01"/>
      <Point x="4345" y="2236" time="16029361.02"/>
      <Point x="4362" y="2239" time="16029361.04"/>
      <Point x="4379" y="2241" time="16029361.05"/>
    </Stroke>
    <Stroke colour="black" start_time="16029363.68" end_time="16029364.27">
      <Point x="4556" y="2125" time="16029363.68"/>
      <Point x="4559" y="2135" time="16029363.70"/>
      <Point x="4560" y="2150" time="16029363.72"/>
      <Point x="4564" y="2169" time="16029363.73"/>
      <Point x="4566" y="2188" time="16029363.75"/>
      <Point x="4576" y="2212" time="16029363.76"/>
      <Point x="4577" y="2234" time="16029363.78"/>
      <Point x="4583" y="2254" time="16029363.79"/>
      <Point x="4584" y="2267" time="16029363.80"/>
      <Point x="4590" y="2274" time="16029363.82"/>
      <Point x="4590" y="2273" time="16029363.83"/>
      <Point x="4594" y="2265" time="16029363.85"/>
      <Point x="4599" y="2251" time="16029363.86"/>
      <Point x="4607" y="2229" time="16029363.88"/>
      <Point x="4611" y="2206" time="16029363.89"/>
      <Point x="4613" y="2187" time="16029363.91"/>
      <Point x="4618" y="2176" time="16029363.92"/>
      <Point x="4627" y="2171" time="16029363.93"/>
      <Point x="4629" y="2166" time="16029363.95"/>
      <Point x="4635" y="2164" time="16029363.97"/>
      <Point x="4639" y="2166" time="16029363.98"/>
      <Point x="4648" y="2174" time="16029363.99"/>
      <Point x="4657" y="2190" time="16029364.01"/>
      <Point x="4664" y="2210" time="16029364.02"/>
      <Point x="4669" y="2233" time="16029364.04"/>
      <Point x="4681" y="2252" time="16029364.05"/>
      <Point x="4685" y="2260" time="16029364.07"/>
      <Point x="4683" y="2257" time="16029364.08"/>
      <Point x="4686" y="2251" time="16029364.09"/>
      <Point x="4698" y="2233" time="16029364.11"/>
      <Point x="4702" y="2209" time="16029364.12"/>
      <Point x="4712" y="2183" time="16029364.14"/>
      <Point x="4722" y="2157" time="16029364.15"/>
      <Point x="4727" y="2130" time="16029364.17"/>
      <Point x="4731" y="2113" time="16029364.18"/>
      <Point x="4734" y="2099" time="16029364.20"/>
      <Point x="4737" y="2093" time="16029364.21"/>
      <Point x="4737" y="2086" time="16029364.23"/>
      <Point x="4742" y="2084" time="16029364.24"/>
      <Point x="4746" y="2084" time="16029364.25"/>
      <Point x="4749" y="2088" time="16029364.27"/>
    </Stroke>
    <Stroke colour="black" start_time="16029364.45" end_time="16029364.86">
      <Point x="4827" y="2178" time="16029364.45"/>
      <Point x="4837" y="2177" time="16029364.46"/>
      <Point x="4840" y="2173" time="16029364.48"/>
      <Point x="4838" y="2168" time="16029364.49"/>
      <Point x="4836" y="2162" time="16029364.51"/>
      <Point x="4833" y="2151" time="16029364.52"/>
      <Point x="4821" y="2139" time="16029364.54"/>
      <Point x="4809" y="2128" time="16029364.55"/>
      <Point x="4796" y="2125" time="16029364.57"/>
      <Point x="4790" y="2130" time="16029364.58"/>
      <Point x="4784" y="2142" time="16029364.59"/>
      <Point x="4777" y="2154" time="16029364.61"/>
      <Point x="4777" y="2171" time="16029364.63"/>
      <Point x="4772" y="2190" time="16029364.64"/>
      <Point x="4770" y="2208" time="16029364.65"/>
      <Point x="4772" y="2229" time="16029364.67"/>
      <Point x="4774" y="2250" time="16029364.68"/>
      <Point x="4785" y="2271" time="16029364.70"/>
      <Point x="4794" y="2282" time="16029364.71"/>
      <Point x="4801" y="2283" time="16029364.73"/>
      <Point x="4819" y="2277" time="16029364.74"/>
      <Point x="4829" y="2260" time="16029364.76"/>
      <Point x="4840" y="2239" time="16029364.77"/>
      <Point x="4847" y="2219" time="16029364.79"/>
      <Point x="4850" y="2203" time="16029364.80"/>
      <Point x="4850" y="2186" time="16029364.81"/>
      <Point x="4842" y="2167" time="16029364.83"/>
      <Point x="4836" y="2154" time="16029364.84"/>
      <Point x="4825" y="2140" time="16029364.86"/>
    </Stroke>
    <Stroke colour="black" start_time="16029365.08" end_time="16029365.49">
      <Point x="4898" y="2148" time="16029365.08"/>
      <Point x="4899" y="2147" time="16029365.10"/>
      <Point x="4902" y="2149" time="16029365.11"/>
      <Point x="4898" y="2157" time="16029365.13"/>
      <Point x="4898" y="2174" time="16029365.14"/>
      <Point x="4895" y="2196" time="16029365.16"/>
      <Point x="4896" y="2221" time="16029365.17"/>
      <Point x="4896" y="2246" time="16029365.18"/>
      <Point x="4907" y="2268" time="16029365.20"/>
      <Point x="4911" y="2277" time="16029365.22"/>
      <Point x="4915" y="2277" time="16029365.23"/>
      <Point x="4918" y="2273" time="16029365.24"/>
      <Point x="4928" y="2254" time="16029365.26"/>
      <Point x="4939" y="2225" time="16029365.27"/>
      <Point x="4945" y="2188" time="16029365.29"/>
      <Point x="4944" y="2155" time="16029365.30"/>
      <Point x="4944" y="2136" time="16029365.32"/>
      <Point x="4941" y="2127" time="16029365.33"/>
      <Point x="4944" y="2128" time="16029365.35"/>
      <Point x="4943" y="2132" time="16029365.36"/>
      <Point x="4939" y="2147" time="16029365.37"/>
      <Point x="4944" y="2174" time="16029365.39"/>
      <Point x="4947" y="2201" time="16029365.41"/>
      <Point x="4949" y="2232" time="16029365.42"/>
      <Point x="4956" y="2262" time="16029365.43"/>
      <Point x="4957" y="2276" time="16029365.44"/>
      <Point x="4963" y="2283" time="16029365.46"/>
      <Point x="4961" y="2277" time="16029365.47"/>
      <Point x="4967" y="2258" time="16029365.49"/>
    </Stroke>
    <Stroke colour="black" start_time="16029365.62" end_time="16029365.80">
      <Point x="4970" y="1954" time="16029365.62"/>
      <Point x="4975" y="1954" time="16029365.64"/>
      <Point x="4982" y="1958" time="16029365.65"/>
      <Point x="4988" y="1973" time="16029365.66"/>
      <Point x="4994" y="1999" time="16029365.68"/>
      <Point x="4994" y="2034" time="16029365.69"/>
      <Point x="5002" y="2076" time="16029365.71"/>
      <Point x="5014" y="2123" time="16029365.72"/>
      <Point x="5026" y="2171" time="16029365.74"/>
      <Point x="5036" y="2211" time="16029365.75"/>
      <Point x="5045" y="2239" time="16029365.76"/>
      <Point x="5047" y="2253" time="16029365.78"/>
      <Point x="5049" y="2249" time="16029365.80"/>
    </Stroke>
    <Stroke colour="black" start_time="16029366.06" end_time="16029366.65">
      <Point x="5140" y="2185" time="16029366.06"/>
      <Point x="5148" y="2178" time="16029366.09"/>
      <Point x="5149" y="2168" time="16029366.11"/>
      <Point x="5138" y="2152" time="16029366.12"/>
      <Point x="5127" y="2129" time="16029366.14"/>
      <Point x="5114" y="2109" time="16029366.15"/>
      <Point x="5105" y="2101" time="16029366.17"/>
      <Point x="5094" y="2105" time="16029366.18"/>
      <Point x="5087" y="2119" time="16029366.20"/>
      <Point x="5082" y="2140" time="16029366.21"/>
      <Point x="5081" y="2161" time="16029366.22"/>
      <Point x="5078" y="2182" time="16029366.24"/>
      <Point x="5078" y="2202" time="16029366.26"/>
      <Point x="5084" y="2224" time="16029366.27"/>
      <Point x="5091" y="2246" time="16029366.28"/>
      <Point x="5093" y="2259" time="16029366.30"/>
      <Point x="5102" y="2267" time="16029366.31"/>
      <Point x="5110" y="2270" time="16029366.33"/>
      <Point x="5115" y="2268" time="16029366.34"/>
      <Point x="5123" y="2261" time="16029366.36"/>
      <Point x="5138" y="2242" time="16029366.37"/>
      <Point x="5142" y="2217" time="16029366.38"/>
      <Point x="5156" y="2179" time="16029366.40"/>
      <Point x="5158" y="2129" time="16029366.41"/>
      <Point x="5163" y="2082" time="16029366.43"/>
      <Point x="5160" y="2041" time="16029366.44"/>
      <Point x="5154" y="2014" time="16029366.45"/>
      <Point x="5154" y="2005" time="16029366.47"/>
      <Point x="5154" y="2006" time="16029366.49"/>
      <Point x="5156" y="2010" time="16029366.50"/>
      <Point x="5156" y="2029" time="16029366.52"/>
      <Point x="5156" y="2057" time="16029366.53"/>
      <Point x="5161" y="2096" time="16029366.54"/>
      <Point x="5166" y="2140" time="16029366.56"/>
      <Point x="5167" y="2192" time="16029366.57"/>
      <Point x="5177" y="2227" time="16029366.59"/>
      <Point x="5178" y="2250" time="16029366.60"/>
      <Point x="5178" y="2260" time="16029366.62"/>
      <Point x="5178" y="2260" time="16029366.63"/>
      <Point x="5176" y="2255" time="16029366.65"/>
    </Stroke>
    <Stroke colour="black" start_time="16029366.83" end_time="16029367.24">
      <Point x="5209" y="2162" time="16029366.83"/>
      <Point x="5216" y="2165" time="16029366.85"/>
      <Point x="5219" y="2168" time="16029366.86"/>
      <Point x="5214" y="2179" time="16029366.87"/>
      <Point x="5209" y="2198" time="16029366.89"/>
      <Point x="5214" y="2214" time="16029366.90"/>
      <Point x="5211" y="2230" time="16029366.92"/>
      <Point x="5212" y="2246" time="16029366.93"/>
      <Point x="5210" y="2258" time="16029366.95"/>
      <Point x="5210" y="2259" time="16029366.96"/>
      <Point x="5215" y="2258" time="16029366.97"/>
      <Point x="5216" y="2246" time="16029366.99"/>
      <Point x="5219" y="2222" time="16029367.01"/>
      <Point x="5226" y="2191" time="16029367.02"/>
      <Point x="5233" y="2166" time="16029367.03"/>
      <Point x="5240" y="2151" time="16029367.05"/>
      <Point x="5254" y="2142" time="16029367.06"/>
      <Point x="5259" y="2141" time="16029367.08"/>
      <Point x="5267" y="2142" time="16029367.09"/>
      <Point x="5281" y="2177" time="16029367.12"/>
      <Point x="5282" y="2204" time="16029367.13"/>
      <Point x="5286" y="2231" time="16029367.15"/>
      <Point x="5290" y="2250" time="16029367.17"/>
      <Point x="5294" y="2262" time="16029367.18"/>
      <Point x="5290" y="2260" time="16029367.19"/>
      <Point x="5291" y="2257" time="16029367.21"/>
      <Point x="5298" y="2245" time="16029367.22"/>
      <Point x="5303" y="2224" time="16029367.24"/>
    </Stroke>
    <Stroke colour="black" start_time="16029367.43" end_time="16029367.49">
      <Point x="5326" y="2002" time="16029367.43"/>
      <Point x="5330" y="2003" time="16029367.45"/>
      <Point x="5333" y="2006" time="16029367.46"/>
      <Point x="5333" y="2014" time="16029367.47"/>
      <Point x="5327" y="2029" time="16029367.49"/>
    </Stroke>
    <Stroke colour="black" start_time="16029367.77" end_time="16029367.94">
      <Point x="5395" y="1984" time="16029367.77"/>
      <Point x="5395" y="1992" time="16029367.78"/>
      <Point x="5397" y="2009" time="16029367.80"/>
      <Point x="5396" y="2032" time="16029367.81"/>
      <Point x="5396" y="2060" time="16029367.83"/>
      <Point x="5399" y="2094" time="16029367.87"/>
      <Point x="5408" y="2133" time="16029367.87"/>
      <Point x="5410" y="2176" time="16029367.87"/>
      <Point x="5414" y="2205" time="16029367.88"/>
      <Point x="5417" y="2228" time="16029367.90"/>
      <Point x="5419" y="2233" time="16029367.91"/>
      <Point x="5422" y="2227" time="16029367.93"/>
      <Point x="5422" y="2215" time="16029367.94"/>
    </Stroke>
    <Stroke colour="black" start_time="16029368.09" end_time="16029368.21">
      <Point x="5407" y="2144" time="16029368.09"/>
      <Point x="5407" y="2152" time="16029368.11"/>
      <Point x="5405" y="2157" time="16029368.12"/>
      <Point x="5400" y="2159" time="16029368.13"/>
      <Point x="5396" y="2149" time="16029368.15"/>
      <Point x="5385" y="2145" time="16029368.17"/>
      <Point x="5378" y="2141" time="16029368.18"/>
      <Point x="5373" y="2141" time="16029368.19"/>
      <Point x="5365" y="2140" time="16029368.21"/>
    </Stroke>
    <Stroke colour="black" start_time="16029368.94" end_time="16029368.94">
      <Point x="5663" y="2179" time="16029368.94"/>
    </Stroke>
    <Stroke colour="black" start_time="16029369.01" end_time="16029369.53">
      <Point x="5670" y="2152" time="16029369.01"/>
      <Point x="5661" y="2143" time="16029369.02"/>
      <Point x="5651" y="2137" time="16029369.04"/>
      <Point x="5643" y="2136" time="16029369.05"/>
      <Point x="5636" y="2143" time="16029369.06"/>
      <Point x="5629" y="2149" time="16029369.09"/>
      <Point x="5622" y="2162" time="16029369.11"/>
      <Point x="5613" y="2174" time="16029369.12"/>
      <Point x="5608" y="2185" time="16029369.13"/>
      <Point x="5611" y="2198" time="16029369.15"/>
      <Point x="5611" y="2207" time="16029369.16"/>
      <Point x="5615" y="2217" time="16029369.18"/>
      <Point x="5620" y="2227" time="16029369.19"/>
      <Point x="5631" y="2233" time="16029369.21"/>
      <Point x="5639" y="2234" time="16029369.22"/>
      <Point x="5648" y="2233" time="16029369.23"/>
      <Point x="5660" y="2225" time="16029369.25"/>
      <Point x="5670" y="2212" time="16029369.26"/>
      <Point x="5673" y="2196" time="16029369.28"/>
      <Point x="5678" y="2184" time="16029369.29"/>
      <Point x="5680" y="2183" time="16029369.31"/>
      <Point x="5676" y="2179" time="16029369.32"/>
      <Point x="5676" y="2181" time="16029369.34"/>
      <Point x="5675" y="2181" time="16029369.35"/>
      <Point x="5676" y="2190" time="16029369.37"/>
      <Point x="5675" y="2213" time="16029369.38"/>
      <Point x="5673" y="2246" time="16029369.39"/>
      <Point x="5675" y="2289" time="16029369.41"/>
      <Point x="5672" y="2333" time="16029369.42"/>
      <Point x="5679" y="2376" time="16029369.44"/>
      <Point x="5675" y="2410" time="16029369.45"/>
      <Point x="5676" y="2435" time="16029369.47"/>
      <Point x="5674" y="2449" time="16029369.48"/>
      <Point x="5676" y="2453" time="16029369.50"/>
      <Point x="5672" y="2451" time="16029369.51"/>
      <Point x="5676" y="2445" time="16029369.53"/>
    </Stroke>
    <Stroke colour="black" start_time="16029369.79" end_time="16029370.20">
      <Point x="5749" y="2152" time="16029369.79"/>
      <Point x="5752" y="2155" time="16029369.81"/>
      <Point x="5750" y="2159" time="16029369.82"/>
      <Point x="5747" y="2166" time="16029369.84"/>
      <Point x="5744" y="2183" time="16029369.86"/>
      <Point x="5744" y="2205" time="16029369.87"/>
      <Point x="5743" y="2225" time="16029369.88"/>
      <Point x="5750" y="2241" time="16029369.90"/>
      <Point x="5760" y="2256" time="16029369.91"/>
      <Point x="5766" y="2263" time="16029369.93"/>
      <Point x="5770" y="2263" time="16029369.94"/>
      <Point x="5783" y="2263" time="16029369.96"/>
      <Point x="5815" y="2223" time="16029369.98"/>
      <Point x="5823" y="2193" time="16029370.00"/>
      <Point x="5828" y="2171" time="16029370.02"/>
      <Point x="5832" y="2160" time="16029370.03"/>
      <Point x="5835" y="2154" time="16029370.04"/>
      <Point x="5834" y="2155" time="16029370.06"/>
      <Point x="5837" y="2159" time="16029370.07"/>
      <Point x="5836" y="2170" time="16029370.09"/>
      <Point x="5841" y="2189" time="16029370.10"/>
      <Point x="5844" y="2205" time="16029370.12"/>
      <Point x="5844" y="2223" time="16029370.13"/>
      <Point x="5844" y="2235" time="16029370.14"/>
      <Point x="5844" y="2243" time="16029370.16"/>
      <Point x="5848" y="2246" time="16029370.18"/>
      <Point x="5857" y="2244" time="16029370.19"/>
      <Point x="5858" y="2231" time="16029370.20"/>
    </Stroke>
    <Stroke colour="black" start_time="16029370.29" end_time="16029370.68">
      <Point x="5861" y="2195" time="16029370.29"/>
      <Point x="5863" y="2200" time="16029370.30"/>
      <Point x="5875" y="2203" time="16029370.32"/>
      <Point x="5880" y="2203" time="16029370.34"/>
      <Point x="5885" y="2199" time="16029370.35"/>
      <Point x="5894" y="2190" time="16029370.36"/>
      <Point x="5899" y="2178" time="16029370.38"/>
      <Point x="5906" y="2169" time="16029370.39"/>
      <Point x="5910" y="2160" time="16029370.41"/>
      <Point x="5913" y="2153" time="16029370.42"/>
      <Point x="5911" y="2147" time="16029370.44"/>
      <Point x="5905" y="2141" time="16029370.45"/>
      <Point x="5898" y="2137" time="16029370.46"/>
      <Point x="5890" y="2136" time="16029370.48"/>
      <Point x="5880" y="2139" time="16029370.50"/>
      <Point x="5872" y="2149" time="16029370.51"/>
      <Point x="5867" y="2161" time="16029370.52"/>
      <Point x="5865" y="2176" time="16029370.54"/>
      <Point x="5863" y="2190" time="16029370.55"/>
      <Point x="5866" y="2204" time="16029370.57"/>
      <Point x="5865" y="2217" time="16029370.58"/>
      <Point x="5870" y="2224" time="16029370.60"/>
      <Point x="5873" y="2228" time="16029370.61"/>
      <Point x="5885" y="2231" time="16029370.62"/>
      <Point x="5896" y="2235" time="16029370.64"/>
      <Point x="5908" y="2237" time="16029370.65"/>
      <Point x="5925" y="2240" time="16029370.67"/>
      <Point x="5933" y="2240" time="16029370.68"/>
    </Stroke>
    <Stroke colour="black" start_time="16029370.86" end_time="16029371.21">
      <Point x="5987" y="2141" time="16029370.86"/>
      <Point x="5991" y="2143" time="16029370.87"/>
      <Point x="5991" y="2143" time="16029370.89"/>
      <Point x="5986" y="2143" time="16029370.90"/>
      <Point x="5981" y="2144" time="16029370.92"/>
      <Point x="5977" y="2145" time="16029370.93"/>
      <Point x="5972" y="2148" time="16029370.95"/>
      <Point x="5964" y="2154" time="16029370.96"/>
      <Point x="5961" y="2163" time="16029370.98"/>
      <Point x="5966" y="2174" time="16029370.99"/>
      <Point x="5967" y="2181" time="16029371.01"/>
      <Point x="5969" y="2188" time="16029371.02"/>
      <Point x="5974" y="2195" time="16029371.03"/>
      <Point x="5979" y="2203" time="16029371.05"/>
      <Point x="5984" y="2214" time="16029371.06"/>
      <Point x="5991" y="2224" time="16029371.08"/>
      <Point x="5996" y="2236" time="16029371.09"/>
      <Point x="6001" y="2243" time="16029371.11"/>
      <Point x="6000" y="2246" time="16029371.12"/>
      <Point x="5995" y="2248" time="16029371.13"/>
      <Point x="5991" y="2246" time="16029371.15"/>
      <Point x="5978" y="2246" time="16029371.16"/>
      <Point x="5965" y="2248" time="16029371.18"/>
      <Point x="5953" y="2243" time="16029371.19"/>
      <Point x="5943" y="2237" time="16029371.21"/>
    </Stroke>
    <Stroke colour="black" start_time="16029371.44" end_time="16029371.62">
      <Point x="6051" y="2032" time="16029371.44"/>
      <Point x="6066" y="2051" time="16029371.45"/>
      <Point x="6065" y="2075" time="16029371.47"/>
      <Point x="6067" y="2102" time="16029371.49"/>
      <Point x="6075" y="2127" time="16029371.50"/>
      <Point x="6073" y="2154" time="16029371.51"/>
      <Point x="6078" y="2183" time="16029371.53"/>
      <Point x="6080" y="2210" time="16029371.54"/>
      <Point x="6081" y="2228" time="16029371.56"/>
      <Point x="6086" y="2239" time="16029371.57"/>
      <Point x="6086" y="2239" time="16029371.59"/>
      <Point x="6083" y="2233" time="16029371.60"/>
      <Point x="6089" y="2220" time="16029371.62"/>
    </Stroke>
    <Stroke colour="black" start_time="16029371.72" end_time="16029371.83">
      <Point x="6107" y="2133" time="16029371.72"/>
      <Point x="6106" y="2135" time="16029371.73"/>
      <Point x="6105" y="2137" time="16029371.76"/>
      <Point x="6095" y="2139" time="16029371.78"/>
      <Point x="6086" y="2141" time="16029371.79"/>
      <Point x="6078" y="2141" time="16029371.81"/>
      <Point x="6070" y="2139" time="16029371.82"/>
      <Point x="6062" y="2137" time="16029371.83"/>
    </Stroke>
    <Stroke colour="black" start_time="16029372.05" end_time="16029372.17">
      <Point x="6156" y="2150" time="16029372.05"/>
      <Point x="6160" y="2172" time="16029372.07"/>
      <Point x="6160" y="2195" time="16029372.08"/>
      <Point x="6165" y="2215" time="16029372.10"/>
      <Point x="6164" y="2227" time="16029372.11"/>
      <Point x="6162" y="2232" time="16029372.13"/>
      <Point x="6162" y="2232" time="16029372.14"/>
      <Point x="6157" y="2222" time="16029372.15"/>
      <Point x="6164" y="2205" time="16029372.17"/>
    </Stroke>
    <Stroke colour="black" start_time="16029372.30" end_time="16029372.36">
      <Point x="6161" y="2024" time="16029372.30"/>
      <Point x="6168" y="2026" time="16029372.32"/>
      <Point x="6161" y="2024" time="16029372.33"/>
      <Point x="6162" y="2020" time="16029372.35"/>
      <Point x="6159" y="2017" time="16029372.36"/>
    </Stroke>
    <Stroke colour="black" start_time="16029372.75" end_time="16029372.98">
      <Point x="6256" y="2135" time="16029372.75"/>
      <Point x="6248" y="2145" time="16029372.76"/>
      <Point x="6247" y="2157" time="16029372.78"/>
      <Point x="6247" y="2171" time="16029372.80"/>
      <Point x="6249" y="2186" time="16029372.81"/>
      <Point x="6247" y="2202" time="16029372.83"/>
      <Point x="6258" y="2219" time="16029372.84"/>
      <Point x="6261" y="2231" time="16029372.86"/>
      <Point x="6271" y="2239" time="16029372.87"/>
      <Point x="6280" y="2240" time="16029372.88"/>
      <Point x="6292" y="2231" time="16029372.90"/>
      <Point x="6300" y="2212" time="16029372.91"/>
      <Point x="6304" y="2188" time="16029372.93"/>
      <Point x="6299" y="2169" time="16029372.94"/>
      <Point x="6295" y="2154" time="16029372.96"/>
      <Point x="6287" y="2142" time="16029372.97"/>
      <Point x="6280" y="2138" time="16029372.98"/>
    </Stroke>
    <Stroke colour="black" start_time="16029373.22" end_time="16029373.22">
      <Point x="6352" y="2152" time="16029373.22"/>
    </Stroke>
    <Stroke colour="black" start_time="16029373.26" end_time="16029373.60">
      <Point x="6359" y="2178" time="16029373.26"/>
      <Point x="6358" y="2193" time="16029373.28"/>
      <Point x="6354" y="2203" time="16029373.29"/>
      <Point x="6355" y="2210" time="16029373.30"/>
      <Point x="6355" y="2213" time="16029373.32"/>
      <Point x="6351" y="2211" time="16029373.33"/>
      <Point x="6355" y="2210" time="16029373.35"/>
      <Point x="6354" y="2203" time="16029373.36"/>
      <Point x="6364" y="2188" time="16029373.38"/>
      <Point x="6370" y="2171" time="16029373.39"/>
      <Point x="6374" y="2150" time="16029373.40"/>
      <Point x="6384" y="2136" time="16029373.42"/>
      <Point x="6391" y="2129" time="16029373.43"/>
      <Point x="6398" y="2132" time="16029373.45"/>
      <Point x="6404" y="2140" time="16029373.46"/>
      <Point x="6414" y="2157" time="16029373.48"/>
      <Point x="6413" y="2171" time="16029373.49"/>
      <Point x="6415" y="2190" time="16029373.51"/>
      <Point x="6416" y="2210" time="16029373.52"/>
      <Point x="6411" y="2222" time="16029373.54"/>
      <Point x="6412" y="2229" time="16029373.55"/>
      <Point x="6408" y="2231" time="16029373.57"/>
      <Point x="6409" y="2227" time="16029373.58"/>
      <Point x="6413" y="2219" time="16029373.60"/>
    </Stroke>
    <Stroke colour="black" start_time="16029375.78" end_time="16029375.96">
      <Point x="6595" y="2128" time="16029375.78"/>
      <Point x="6594" y="2131" time="16029375.80"/>
      <Point x="6596" y="2137" time="16029375.82"/>
      <Point x="6601" y="2147" time="16029375.83"/>
      <Point x="6610" y="2157" time="16029375.85"/>
      <Point x="6616" y="2164" time="16029375.86"/>
      <Point x="6626" y="2174" time="16029375.88"/>
      <Point x="6633" y="2188" time="16029375.89"/>
      <Point x="6638" y="2197" time="16029375.91"/>
      <Point x="6644" y="2204" time="16029375.92"/>
      <Point x="6643" y="2206" time="16029375.94"/>
      <Point x="6650" y="2203" time="16029375.95"/>
      <Point x="6655" y="2186" time="16029375.96"/>
    </Stroke>
    <Stroke colour="black" start_time="16029376.11" end_time="16029376.29">
      <Point x="6674" y="2121" time="16029376.11"/>
      <Point x="6680" y="2138" time="16029376.12"/>
      <Point x="6679" y="2157" time="16029376.14"/>
      <Point x="6674" y="2179" time="16029376.15"/>
      <Point x="6664" y="2206" time="16029376.17"/>
      <Point x="6656" y="2241" time="16029376.18"/>
      <Point x="6651" y="2279" time="16029376.20"/>
      <Point x="6645" y="2316" time="16029376.21"/>
      <Point x="6644" y="2352" time="16029376.23"/>
      <Point x="6638" y="2376" time="16029376.24"/>
      <Point x="6639" y="2396" time="16029376.25"/>
      <Point x="6636" y="2403" time="16029376.27"/>
      <Point x="6635" y="2405" time="16029376.29"/>
    </Stroke>
    <Stroke colour="black" start_time="16029376.55" end_time="16029376.91">
      <Point x="6797" y="2147" time="16029376.55"/>
      <Point x="6797" y="2144" time="16029376.57"/>
      <Point x="6799" y="2137" time="16029376.59"/>
      <Point x="6794" y="2128" time="16029376.60"/>
      <Point x="6785" y="2120" time="16029376.62"/>
      <Point x="6781" y="2116" time="16029376.63"/>
      <Point x="6770" y="2113" time="16029376.65"/>
      <Point x="6757" y="2113" time="16029376.66"/>
      <Point x="6751" y="2120" time="16029376.68"/>
      <Point x="6743" y="2129" time="16029376.69"/>
      <Point x="6737" y="2145" time="16029376.71"/>
      <Point x="6739" y="2165" time="16029376.72"/>
      <Point x="6739" y="2188" time="16029376.73"/>
      <Point x="6745" y="2207" time="16029376.75"/>
      <Point x="6753" y="2222" time="16029376.76"/>
      <Point x="6762" y="2230" time="16029376.78"/>
      <Point x="6770" y="2232" time="16029376.79"/>
      <Point x="6780" y="2229" time="16029376.81"/>
      <Point x="6795" y="2222" time="16029376.82"/>
      <Point x="6800" y="2206" time="16029376.83"/>
      <Point x="6808" y="2186" time="16029376.85"/>
      <Point x="6806" y="2167" time="16029376.86"/>
      <Point x="6799" y="2151" time="16029376.88"/>
      <Point x="6794" y="2138" time="16029376.89"/>
      <Point x="6794" y="2130" time="16029376.91"/>
    </Stroke>
    <Stroke colour="black" start_time="16029377.17" end_time="16029377.58">
      <Point x="6871" y="2113" time="16029377.17"/>
      <Point x="6880" y="2112" time="16029377.18"/>
      <Point x="6879" y="2113" time="16029377.20"/>
      <Point x="6873" y="2121" time="16029377.22"/>
      <Point x="6872" y="2135" time="16029377.23"/>
      <Point x="6874" y="2142" time="16029377.24"/>
      <Point x="6876" y="2162" time="16029377.26"/>
      <Point x="6881" y="2185" time="16029377.27"/>
      <Point x="6889" y="2207" time="16029377.29"/>
      <Point x="6892" y="2224" time="16029377.30"/>
      <Point x="6898" y="2233" time="16029377.32"/>
      <Point x="6905" y="2234" time="16029377.33"/>
      <Point x="6908" y="2227" time="16029377.35"/>
      <Point x="6919" y="2220" time="16029377.36"/>
      <Point x="6929" y="2203" time="16029377.38"/>
      <Point x="6942" y="2179" time="16029377.39"/>
      <Point x="6946" y="2154" time="16029377.40"/>
      <Point x="6954" y="2130" time="16029377.42"/>
      <Point x="6959" y="2115" time="16029377.43"/>
      <Point x="6956" y="2109" time="16029377.45"/>
      <Point x="6956" y="2111" time="16029377.46"/>
      <Point x="6961" y="2120" time="16029377.48"/>
      <Point x="6963" y="2141" time="16029377.49"/>
      <Point x="6968" y="2161" time="16029377.50"/>
      <Point x="6972" y="2188" time="16029377.52"/>
      <Point x="6971" y="2216" time="16029377.54"/>
      <Point x="6970" y="2233" time="16029377.55"/>
      <Point x="6968" y="2236" time="16029377.56"/>
      <Point x="6960" y="2224" time="16029377.58"/>
    </Stroke>
  </StrokeSet>
</WhiteboardCaptureSession>
