<?xml version="1.0" encoding="ISO-8859-1"?>
<WhiteboardCaptureSession>
  <WhiteboardDescription>
    <SensorLocation corner="top_left"/>
    <DiagonallyOppositeCoords x="5683" y="3269"/>
    <VerticallyOppositeCoords x="1034" y="3269"/>
    <HorizontallyOppositeCoords x="5683" y="2639"/>
  </WhiteboardDescription>
  <StrokeSet>
    <Stroke colour="black" start_time="1993.56" end_time="1994.27">
      <Point x="1224" y="3089" time="1993.56"/>
      <Point x="1204" y="3078" time="1993.58"/>
      <Point x="1177" y="3075" time="1993.60"/>
      <Point x="1145" y="3083" time="1993.61"/>
      <Point x="1108" y="3105" time="1993.65"/>
      <Point x="1075" y="3141" time="1993.65"/>
      <Point x="1047" y="3181" time="1993.66"/>
      <Point x="1034" y="3224" time="1993.67"/>
      <Point x="1034" y="3252" time="1993.68"/>
      <Point x="1047" y="3269" time="1993.70"/>
      <Point x="1071" y="3264" time="1993.72"/>
      <Point x="1102" y="3253" time="1993.73"/>
      <Point x="1134" y="3224" time="1993.75"/>
      <Point x="1165" y="3192" time="1993.76"/>
      <Point x="1192" y="3163" time="1993.78"/>
      <Point x="1209" y="3138" time="1993.79"/>
      <Point x="1217" y="3122" time="1993.81"/>
      <Point x="1216" y="3118" time="1993.82"/>
      <Point x="1209" y="3125" time="1993.84"/>
      <Point x="1198" y="3146" time="1993.85"/>
      <Point x="1191" y="3175" time="1993.87"/>
      <Point x="1189" y="3203" time="1993.88"/>
      <Point x="1194" y="3222" time="1993.95"/>
      <Point x="1206" y="3230" time="1993.95"/>
      <Point x="1220" y="3221" time="1993.95"/>
      <Point x="1236" y="3209" time="1993.95"/>
      <Point x="1253" y="3192" time="1993.96"/>
      <Point x="1266" y="3163" time="1993.97"/>
      <Point x="1276" y="3138" time="1993.99"/>
      <Point x="1283" y="3126" time="1994.00"/>
      <Point x="1286" y="3125" time="1994.02"/>
      <Point x="1287" y="3134" time="1994.03"/>
      <Point x="1288" y="3153" time="1994.05"/>
      <Point x="1288" y="3177" time="1994.06"/>
      <Point x="1288" y="3202" time="1994.08"/>
      <Point x="1291" y="3217" time="1994.09"/>
      <Point x="1296" y="3221" time="1994.11"/>
      <Point x="1303" y="3216" time="1994.12"/>
      <Point x="1315" y="3199" time="1994.14"/>
      <Point x="1329" y="3170" time="1994.16"/>
      <Point x="1341" y="3146" time="1994.17"/>
      <Point x="1349" y="3136" time="1994.18"/>
      <Point x="1354" y="3140" time="1994.20"/>
      <Point x="1360" y="3156" time="1994.22"/>
      <Point x="1364" y="3171" time="1994.23"/>
      <Point x="1372" y="3190" time="1994.24"/>
      <Point x="1383" y="3202" time="1994.26"/>
      <Point x="1401" y="3208" time="1994.27"/>
    </Stroke>
    <Stroke colour="black" start_time="1994.38" end_time="1994.56">
      <Point x="1544" y="3141" time="1994.38"/>
      <Point x="1539" y="3141" time="1994.40"/>
      <Point x="1527" y="3143" time="1994.41"/>
      <Point x="1511" y="3150" time="1994.43"/>
      <Point x="1489" y="3156" time="1994.44"/>
      <Point x="1469" y="3172" time="1994.46"/>
      <Point x="1455" y="3189" time="1994.47"/>
      <Point x="1448" y="3210" time="1994.49"/>
      <Point x="1450" y="3223" time="1994.50"/>
      <Point x="1460" y="3225" time="1994.52"/>
      <Point x="1483" y="3222" time="1994.53"/>
      <Point x="1510" y="3206" time="1994.55"/>
      <Point x="1539" y="3177" time="1994.56"/>
    </Stroke>
    <Stroke colour="black" start_time="1994.67" end_time="1994.85">
      <Point x="1578" y="2948" time="1994.67"/>
      <Point x="1573" y="2949" time="1994.68"/>
      <Point x="1568" y="2954" time="1994.70"/>
      <Point x="1565" y="2979" time="1994.71"/>
      <Point x="1563" y="3012" time="1994.73"/>
      <Point x="1568" y="3056" time="1994.74"/>
      <Point x="1575" y="3099" time="1994.76"/>
      <Point x="1583" y="3139" time="1994.77"/>
      <Point x="1592" y="3169" time="1994.85"/>
    </Stroke>
    <Stroke colour="black" start_time="1995.23" end_time="1995.58">
      <Point x="2018" y="2871" time="1995.23"/>
      <Point x="2014" y="2901" time="1995.25"/>
      <Point x="2014" y="2952" time="1995.27"/>
      <Point x="2017" y="3011" time="1995.28"/>
      <Point x="2015" y="3053" time="1995.30"/>
      <Point x="2021" y="3088" time="1995.31"/>
      <Point x="2027" y="3112" time="1995.33"/>
      <Point x="2029" y="3112" time="1995.34"/>
      <Point x="2036" y="3109" time="1995.36"/>
      <Point x="2045" y="3090" time="1995.37"/>
      <Point x="2059" y="3063" time="1995.39"/>
      <Point x="2082" y="3043" time="1995.40"/>
      <Point x="2105" y="3031" time="1995.42"/>
      <Point x="2128" y="3031" time="1995.43"/>
      <Point x="2145" y="3037" time="1995.45"/>
      <Point x="2154" y="3051" time="1995.46"/>
      <Point x="2154" y="3073" time="1995.48"/>
      <Point x="2142" y="3098" time="1995.49"/>
      <Point x="2122" y="3117" time="1995.51"/>
      <Point x="2100" y="3129" time="1995.52"/>
      <Point x="2078" y="3137" time="1995.54"/>
      <Point x="2059" y="3135" time="1995.56"/>
      <Point x="2047" y="3126" time="1995.57"/>
      <Point x="2048" y="3122" time="1995.58"/>
    </Stroke>
    <Stroke colour="black" start_time="1995.72" end_time="1995.96">
      <Point x="2289" y="3027" time="1995.72"/>
      <Point x="2287" y="3024" time="1995.73"/>
      <Point x="2276" y="3024" time="1995.75"/>
      <Point x="2253" y="3034" time="1995.76"/>
      <Point x="2231" y="3055" time="1995.78"/>
      <Point x="2214" y="3075" time="1995.80"/>
      <Point x="2208" y="3091" time="1995.81"/>
      <Point x="2213" y="3101" time="1995.82"/>
      <Point x="2233" y="3111" time="1995.84"/>
      <Point x="2256" y="3102" time="1995.86"/>
      <Point x="2283" y="3086" time="1995.87"/>
      <Point x="2299" y="3062" time="1995.88"/>
      <Point x="2306" y="3047" time="1995.90"/>
      <Point x="2306" y="3042" time="1995.92"/>
      <Point x="2297" y="3037" time="1995.93"/>
      <Point x="2283" y="3034" time="1995.94"/>
      <Point x="2277" y="3033" time="1995.96"/>
    </Stroke>
    <Stroke colour="black" start_time="1996.12" end_time="1996.27">
      <Point x="2457" y="2816" time="1996.12"/>
      <Point x="2459" y="2820" time="1996.14"/>
      <Point x="2453" y="2832" time="1996.16"/>
      <Point x="2449" y="2865" time="1996.17"/>
      <Point x="2445" y="2907" time="1996.18"/>
      <Point x="2442" y="2958" time="1996.20"/>
      <Point x="2441" y="3016" time="1996.22"/>
      <Point x="2440" y="3061" time="1996.23"/>
      <Point x="2442" y="3091" time="1996.24"/>
      <Point x="2445" y="3103" time="1996.26"/>
      <Point x="2448" y="3101" time="1996.27"/>
    </Stroke>
    <Stroke colour="black" start_time="1996.38" end_time="1996.53">
      <Point x="2517" y="2807" time="1996.38"/>
      <Point x="2523" y="2794" time="1996.40"/>
      <Point x="2527" y="2797" time="1996.41"/>
      <Point x="2524" y="2817" time="1996.43"/>
      <Point x="2523" y="2858" time="1996.44"/>
      <Point x="2516" y="2907" time="1996.46"/>
      <Point x="2516" y="2970" time="1996.47"/>
      <Point x="2516" y="3028" time="1996.49"/>
      <Point x="2517" y="3073" time="1996.50"/>
      <Point x="2523" y="3101" time="1996.52"/>
      <Point x="2525" y="3109" time="1996.53"/>
    </Stroke>
    <Stroke colour="black" start_time="1996.66" end_time="1996.74">
      <Point x="2393" y="2960" time="1996.66"/>
      <Point x="2406" y="2958" time="1996.68"/>
      <Point x="2441" y="2953" time="1996.70"/>
      <Point x="2492" y="2951" time="1996.71"/>
      <Point x="2547" y="2950" time="1996.73"/>
      <Point x="2602" y="2951" time="1996.74"/>
    </Stroke>
    <Stroke colour="black" start_time="1996.82" end_time="1997.60">
      <Point x="2713" y="2976" time="1996.82"/>
      <Point x="2698" y="2985" time="1996.83"/>
      <Point x="2676" y="2997" time="1996.85"/>
      <Point x="2651" y="3006" time="1996.86"/>
      <Point x="2632" y="3022" time="1996.88"/>
      <Point x="2613" y="3032" time="1996.89"/>
      <Point x="2610" y="3047" time="1996.91"/>
      <Point x="2613" y="3059" time="1996.92"/>
      <Point x="2625" y="3071" time="1996.94"/>
      <Point x="2653" y="3078" time="1996.95"/>
      <Point x="2680" y="3069" time="1996.97"/>
      <Point x="2706" y="3049" time="1996.98"/>
      <Point x="2724" y="3030" time="1997.00"/>
      <Point x="2732" y="3012" time="1997.01"/>
      <Point x="2727" y="3000" time="1997.07"/>
      <Point x="2713" y="2990" time="1997.07"/>
      <Point x="2695" y="2991" time="1997.07"/>
      <Point x="2682" y="2994" time="1997.08"/>
      <Point x="2675" y="2994" time="1997.09"/>
      <Point x="2678" y="2992" time="1997.10"/>
      <Point x="2697" y="2991" time="1997.12"/>
      <Point x="2721" y="2980" time="1997.14"/>
      <Point x="2755" y="2975" time="1997.15"/>
      <Point x="2782" y="2972" time="1997.16"/>
      <Point x="2806" y="2982" time="1997.18"/>
      <Point x="2819" y="2997" time="1997.20"/>
      <Point x="2824" y="3022" time="1997.21"/>
      <Point x="2822" y="3042" time="1997.22"/>
      <Point x="2816" y="3055" time="1997.24"/>
      <Point x="2815" y="3061" time="1997.26"/>
      <Point x="2815" y="3060" time="1997.27"/>
      <Point x="2820" y="3057" time="1997.28"/>
      <Point x="2823" y="3037" time="1997.30"/>
      <Point x="2831" y="3008" time="1997.32"/>
      <Point x="2848" y="2988" time="1997.33"/>
      <Point x="2868" y="2975" time="1997.35"/>
      <Point x="2884" y="2975" time="1997.36"/>
      <Point x="2898" y="2980" time="1997.38"/>
      <Point x="2911" y="2996" time="1997.39"/>
      <Point x="2917" y="3015" time="1997.41"/>
      <Point x="2913" y="3032" time="1997.42"/>
      <Point x="2914" y="3051" time="1997.44"/>
      <Point x="2911" y="3052" time="1997.45"/>
      <Point x="2914" y="3050" time="1997.47"/>
      <Point x="2927" y="3033" time="1997.48"/>
      <Point x="2949" y="3004" time="1997.50"/>
      <Point x="2969" y="2982" time="1997.51"/>
      <Point x="2989" y="2977" time="1997.53"/>
      <Point x="3000" y="2980" time="1997.54"/>
      <Point x="3006" y="2989" time="1997.56"/>
      <Point x="3011" y="3011" time="1997.57"/>
      <Point x="3009" y="3032" time="1997.59"/>
      <Point x="3006" y="3048" time="1997.60"/>
    </Stroke>
    <Stroke colour="black" start_time="1998.16" end_time="1998.41">
      <Point x="3371" y="2936" time="1998.16"/>
      <Point x="3352" y="2941" time="1998.18"/>
      <Point x="3322" y="2950" time="1998.20"/>
      <Point x="3298" y="2970" time="1998.21"/>
      <Point x="3282" y="2992" time="1998.22"/>
      <Point x="3274" y="3013" time="1998.24"/>
      <Point x="3277" y="3031" time="1998.26"/>
      <Point x="3300" y="3044" time="1998.27"/>
      <Point x="3328" y="3037" time="1998.29"/>
      <Point x="3366" y="3017" time="1998.30"/>
      <Point x="3398" y="2991" time="1998.32"/>
      <Point x="3411" y="2965" time="1998.33"/>
      <Point x="3412" y="2948" time="1998.35"/>
      <Point x="3397" y="2930" time="1998.36"/>
      <Point x="3379" y="2918" time="1998.38"/>
      <Point x="3366" y="2914" time="1998.39"/>
      <Point x="3356" y="2911" time="1998.41"/>
    </Stroke>
    <Stroke colour="black" start_time="1998.60" end_time="1998.78">
      <Point x="3533" y="3061" time="1998.60"/>
      <Point x="3528" y="3049" time="1998.61"/>
      <Point x="3522" y="3023" time="1998.63"/>
      <Point x="3522" y="2985" time="1998.64"/>
      <Point x="3517" y="2937" time="1998.66"/>
      <Point x="3515" y="2885" time="1998.68"/>
      <Point x="3526" y="2837" time="1998.69"/>
      <Point x="3550" y="2794" time="1998.70"/>
      <Point x="3583" y="2751" time="1998.72"/>
      <Point x="3624" y="2723" time="1998.74"/>
      <Point x="3667" y="2708" time="1998.75"/>
      <Point x="3701" y="2701" time="1998.76"/>
      <Point x="3728" y="2708" time="1998.78"/>
    </Stroke>
    <Stroke colour="black" start_time="1998.94" end_time="1999.00">
      <Point x="3482" y="2989" time="1998.94"/>
      <Point x="3506" y="2989" time="1998.96"/>
      <Point x="3542" y="2984" time="1998.97"/>
      <Point x="3586" y="2978" time="1998.99"/>
      <Point x="3633" y="2972" time="1999.00"/>
    </Stroke>
    <Stroke colour="black" start_time="1999.36" end_time="1999.50">
      <Point x="4036" y="2689" time="1999.36"/>
      <Point x="4037" y="2694" time="1999.38"/>
      <Point x="4040" y="2715" time="1999.40"/>
      <Point x="4046" y="2750" time="1999.41"/>
      <Point x="4053" y="2791" time="1999.43"/>
      <Point x="4063" y="2846" time="1999.44"/>
      <Point x="4067" y="2902" time="1999.46"/>
      <Point x="4074" y="2958" time="1999.47"/>
      <Point x="4078" y="3001" time="1999.49"/>
      <Point x="4079" y="3023" time="1999.50"/>
    </Stroke>
    <Stroke colour="black" start_time="1999.64" end_time="1999.71">
      <Point x="3998" y="2917" time="1999.64"/>
      <Point x="4001" y="2914" time="1999.65"/>
      <Point x="4020" y="2911" time="1999.67"/>
      <Point x="4052" y="2917" time="1999.68"/>
      <Point x="4087" y="2919" time="1999.70"/>
      <Point x="4126" y="2921" time="1999.71"/>
    </Stroke>
    <Stroke colour="black" start_time="1999.90" end_time="2000.39">
      <Point x="4169" y="2697" time="1999.90"/>
      <Point x="4176" y="2741" time="1999.92"/>
      <Point x="4179" y="2798" time="1999.94"/>
      <Point x="4178" y="2861" time="1999.95"/>
      <Point x="4176" y="2917" time="1999.96"/>
      <Point x="4177" y="2958" time="1999.98"/>
      <Point x="4181" y="2984" time="1999.99"/>
      <Point x="4179" y="2987" time="2000.01"/>
      <Point x="4186" y="2985" time="2000.02"/>
      <Point x="4195" y="2969" time="2000.04"/>
      <Point x="4209" y="2946" time="2000.06"/>
      <Point x="4219" y="2924" time="2000.07"/>
      <Point x="4228" y="2907" time="2000.09"/>
      <Point x="4242" y="2903" time="2000.10"/>
      <Point x="4257" y="2904" time="2000.12"/>
      <Point x="4276" y="2913" time="2000.13"/>
      <Point x="4299" y="2928" time="2000.15"/>
      <Point x="4328" y="2945" time="2000.16"/>
      <Point x="4357" y="2954" time="2000.18"/>
      <Point x="4383" y="2953" time="2000.19"/>
      <Point x="4408" y="2943" time="2000.21"/>
      <Point x="4423" y="2924" time="2000.22"/>
      <Point x="4430" y="2910" time="2000.23"/>
      <Point x="4420" y="2896" time="2000.25"/>
      <Point x="4403" y="2893" time="2000.27"/>
      <Point x="4381" y="2900" time="2000.28"/>
      <Point x="4366" y="2918" time="2000.29"/>
      <Point x="4355" y="2938" time="2000.31"/>
      <Point x="4360" y="2957" time="2000.33"/>
      <Point x="4378" y="2972" time="2000.34"/>
      <Point x="4413" y="2980" time="2000.36"/>
      <Point x="4453" y="2977" time="2000.37"/>
      <Point x="4496" y="2967" time="2000.39"/>
    </Stroke>
    <Stroke colour="black" start_time="2000.75" end_time="2001.10">
      <Point x="4864" y="2663" time="2000.75"/>
      <Point x="4862" y="2674" time="2000.76"/>
      <Point x="4864" y="2707" time="2000.78"/>
      <Point x="4869" y="2750" time="2000.79"/>
      <Point x="4873" y="2801" time="2000.81"/>
      <Point x="4880" y="2861" time="2000.83"/>
      <Point x="4885" y="2908" time="2000.84"/>
      <Point x="4891" y="2935" time="2000.86"/>
      <Point x="4895" y="2948" time="2000.87"/>
      <Point x="4896" y="2946" time="2000.89"/>
      <Point x="4899" y="2943" time="2000.90"/>
      <Point x="4902" y="2919" time="2000.91"/>
      <Point x="4912" y="2890" time="2000.93"/>
      <Point x="4933" y="2869" time="2000.95"/>
      <Point x="4953" y="2852" time="2000.96"/>
      <Point x="4976" y="2848" time="2000.98"/>
      <Point x="4993" y="2851" time="2000.99"/>
      <Point x="5002" y="2860" time="2001.01"/>
      <Point x="5009" y="2877" time="2001.02"/>
      <Point x="5003" y="2893" time="2001.04"/>
      <Point x="4990" y="2912" time="2001.05"/>
      <Point x="4975" y="2926" time="2001.07"/>
      <Point x="4962" y="2931" time="2001.08"/>
      <Point x="4952" y="2931" time="2001.10"/>
    </Stroke>
    <Stroke colour="black" start_time="2001.23" end_time="2001.53">
      <Point x="5131" y="2883" time="2001.23"/>
      <Point x="5129" y="2879" time="2001.25"/>
      <Point x="5122" y="2874" time="2001.26"/>
      <Point x="5107" y="2869" time="2001.27"/>
      <Point x="5089" y="2873" time="2001.29"/>
      <Point x="5069" y="2882" time="2001.31"/>
      <Point x="5057" y="2893" time="2001.32"/>
      <Point x="5050" y="2902" time="2001.34"/>
      <Point x="5055" y="2917" time="2001.35"/>
      <Point x="5070" y="2922" time="2001.37"/>
      <Point x="5096" y="2920" time="2001.38"/>
      <Point x="5121" y="2905" time="2001.40"/>
      <Point x="5144" y="2885" time="2001.41"/>
      <Point x="5156" y="2868" time="2001.43"/>
      <Point x="5158" y="2857" time="2001.44"/>
      <Point x="5148" y="2850" time="2001.46"/>
      <Point x="5131" y="2847" time="2001.47"/>
      <Point x="5105" y="2851" time="2001.49"/>
      <Point x="5091" y="2856" time="2001.50"/>
      <Point x="5088" y="2855" time="2001.52"/>
      <Point x="5093" y="2854" time="2001.53"/>
    </Stroke>
    <Stroke colour="black" start_time="2001.67" end_time="2002.00">
      <Point x="5244" y="2857" time="2001.67"/>
      <Point x="5248" y="2859" time="2001.68"/>
      <Point x="5238" y="2859" time="2001.70"/>
      <Point x="5227" y="2861" time="2001.71"/>
      <Point x="5211" y="2871" time="2001.73"/>
      <Point x="5197" y="2884" time="2001.74"/>
      <Point x="5188" y="2899" time="2001.76"/>
      <Point x="5190" y="2910" time="2001.78"/>
      <Point x="5197" y="2914" time="2001.79"/>
      <Point x="5213" y="2911" time="2001.81"/>
      <Point x="5236" y="2900" time="2001.82"/>
      <Point x="5253" y="2881" time="2001.83"/>
      <Point x="5267" y="2865" time="2001.85"/>
      <Point x="5270" y="2854" time="2001.87"/>
      <Point x="5271" y="2853" time="2001.88"/>
      <Point x="5269" y="2854" time="2001.90"/>
      <Point x="5267" y="2859" time="2001.91"/>
      <Point x="5269" y="2870" time="2001.93"/>
      <Point x="5274" y="2883" time="2001.94"/>
      <Point x="5289" y="2899" time="2001.95"/>
      <Point x="5305" y="2910" time="2001.97"/>
      <Point x="5327" y="2913" time="2001.99"/>
      <Point x="5351" y="2904" time="2002.00"/>
    </Stroke>
    <Stroke colour="black" start_time="2002.16" end_time="2002.31">
      <Point x="5433" y="2639" time="2002.16"/>
      <Point x="5435" y="2651" time="2002.18"/>
      <Point x="5433" y="2678" time="2002.19"/>
      <Point x="5431" y="2714" time="2002.21"/>
      <Point x="5435" y="2761" time="2002.23"/>
      <Point x="5437" y="2813" time="2002.24"/>
      <Point x="5443" y="2864" time="2002.25"/>
      <Point x="5445" y="2900" time="2002.27"/>
      <Point x="5455" y="2921" time="2002.29"/>
      <Point x="5456" y="2926" time="2002.30"/>
      <Point x="5453" y="2924" time="2002.31"/>
    </Stroke>
    <Stroke colour="black" start_time="2002.42" end_time="2002.51">
      <Point x="5352" y="2799" time="2002.42"/>
      <Point x="5360" y="2792" time="2002.43"/>
      <Point x="5384" y="2784" time="2002.45"/>
      <Point x="5410" y="2779" time="2002.47"/>
      <Point x="5449" y="2777" time="2002.48"/>
      <Point x="5491" y="2777" time="2002.49"/>
      <Point x="5532" y="2779" time="2002.51"/>
    </Stroke>
    <Stroke colour="black" start_time="2002.84" end_time="2002.84">
      <Point x="5678" y="2910" time="2002.84"/>
    </Stroke>
    <Stroke colour="black" start_time="2002.87" end_time="2002.89">
      <Point x="5680" y="2907" time="2002.87"/>
      <Point x="5683" y="2907" time="2002.89"/>
    </Stroke>
  </StrokeSet>
</WhiteboardCaptureSession>
